Workbook

Sheet 00_LEEME
A1: Anexo E · Matrices auditables del MVP Marley Coffee HORECA
A2: Versión1.9 ·19-10-2026 · Modelo confirmado: comodato y compra mensual de insumos. Recorrido: Productos C10 → Máquinas C11 → Contacto C03 → Diagnóstico C04. El test15oct corresponde a la versión anterior; no valida estas mejoras.
A4: Hoja | B4: Contenido
A5: 01_ENGAGEMENT | B5: Engagement Score v1.1: 13 eventos M2 + evento 14 (comuna). Calculadora con 3 casos; cambia las celdas amarillas.
A6: 02_ZONAS | B6: Comunas, prioridad geográfica (A, B, C, regiones), puntos, potencial, ejecutiva de zona (ficticia) y ruta (demo).
A7: 03_FINANCIAL | B7: Financial Score v0.1 con pesos editables y cálculo para 20 cuentas ficticias; compara con el valor del prototipo.
A8: 04_KPIS | B8: KPIs comerciales, operacionales, de inbound y de experiencia: fórmula, unidad, ventana, fuente, frecuencia, responsable y umbral.
A9: 05_WORKFLOWS | B9: Workflows de inbound automatizado: gatillador, condición, espera, canal, contenido, supresión y KPI.
A10: 06_CONTENIDOS | B10: Piezas audiovisuales y gráficas por etapa del funnel y segmento, con estado.
A11: 07_TEST_PLAN | B11: Plan de test de usabilidad: tareas críticas, criterio de éxito, métricas y umbrales; cuáles se midieron en la ronda 1 (15-10).
A12: 08_TEST_REGISTRO | B12: Registro real de la ronda 1 (P1 a P5, 15-10-2026) y filas para la ronda 2. El resumen por tarea se calcula solo.
A13: 09_SUS | B13: SUS por participante en la ronda 1 (puntaje registrado por el test) y cuestionario de 10 ítems con su fórmula para la ronda 2.
A14: 10_HALLAZGOS | B14: Hallazgos con frecuencia, impacto, severidad (0–4) y mejora. Ciclo 0 = revisión interna (09 a 12-10); ciclo 1 = test con 5 usuarios (15-10).
A15: 11_COMPARACION | B15: Comparación v3 → v4 → v5 (métricas de diseño verificadas), resultados de la ronda 1 contra umbrales y cambios v5 → v6 después del test.
... A29: Convención | B29: Celdas amarillas = datos que se ingresan. Celdas grises = fórmulas. Participantes del test con código (P1 a P5), sin nombres. Datos de clientes, montos y nombres de ejecutivas: ficticios de demostración.

Sheet 01_ENGAGEMENT
A1: Engagement Score v1.1 · prospectos
A2: 13 eventos y pesos de la tabla M2 (informe MVP corregido, fuente [3]) + evento 14 «comuna» (ajuste 10-10). Cada evento suma una vez; tope 100.
A4: N° | B4: Clave | C4: Evento | D4: Puntos | E4: Regla / control | F4: Caso A (1 = ocurrió) | G4: Caso B (1 = ocurrió) | H4: Caso C (1 = ocurrió) | J4: Desde | K4: Banda | L4: Acción típica
A5: 1 | B5: cotizar | C5: Pulsa «Encontrar mi solución» | D5: 10 | E5: Una vez por contacto. | F5: 1 | G5: 1 | H5: 1 | J5: 0 | K5: Exploración | L5: Contenido y nutrición suave
A6: 2 | B6: form1 | C6: Deja su correo con permiso (formulario 1) | D6: 20 | E6: Solo con correo válido y permiso. | F6: 1 | G6: 1 | H6: 1 | J6: 20 | K6: Identificado | L6: Continuidad automática
A7: 3 | B7: portal | C7: Entra a su portal | D7: 8 | E7: Primera entrada al portal. | F7: 1 | G7: 1 | H7: 1 | J7: 40 | K7: Calificado | L7: Recomendación y seguimiento
A8: 4 | B8: diag_inicio | C8: Inicia el diagnóstico | D8: 5 | E8: Primera respuesta. | F8: 1 | G8: 1 | H8: 1 | J8: 60 | K8: Alta intención | L8: Prioridad comercial
A9: 5 | B9: negocio | C9: Tipo de negocio | D9: 4 | E9: Define fit HORECA. | F9: 1 | G9: 1 | H9: 1 | J9: 80 | K9: Prioridad máxima | L9: Persona del equipo ahora
A10: 6 | B10: volumen | C10: Volumen de tazas | D10: 5 | E10: «No lo sé» cuenta. | F10: 1 | G10: 1 | H10: 1
A11: 7 | B11: operacion | C11: Forma de servicio | D11: 4 | E11: Define formato. | F11: 1 | G11: 1 | H11: 1
A12: 8 | B12: preferencias | C12: Qué quiere ofrecer | D12: 4 | E12: Una vez aunque elija varias. | F12: 1 | G12: 1 | H12: 1
A13: 9 | B13: canal | C13: Confirma correo de contacto | D13: 3 | E13: Correo para seguimiento comercial. | F13: 1 | G13: 1 | H13: 1
A14: 10 | B14: recomendacion | C14: Revisa su recomendación | D14: 8 | E14: Portal con diagnóstico completo. | F14: 1 | G14: 1 | H14: 1
A15: 11 | B15: propuesta | C15: Acepta la propuesta | D15: 15 | E15: Señal comercial para SQL. | F15: 0 | G15: 0 | H15: 0
A16: 12 | B16: ejecutivo | C16: Pide hablar con una persona | D16: 12 | E16: Al elegir cualquier canal humano. | F16: 1 | G16: 1 | H16: 1
A17: 13 | B17: expansion | C17: Elige la propuesta ampliada | D17: 12 | E17: Elige ampliada. | F17: 0 | G17: 0 | H17: 0
A18: 14 | B18: comuna | C18: Comuna del local (evento 14) | D18: según zona | E18: Puntos desde 02_ZONAS. | F18: Las Condes | G18: Santiago Centro | H18: Maipú
C20: Suma eventos M2 | F20: =SUMPRODUCT($D$5:$D$17,F5:F17) | G20: =SUMPRODUCT($D$5:$D$17,G5:G17) | H20: =SUMPRODUCT($D$5:$D$17,H5:H17)
C21: Puntos por comuna | F21: =VLOOKUP(F18,'02_ZONAS'!$A$5:$D$31,4,FALSE) | G21: =VLOOKUP(G18,'02_ZONAS'!$A$5:$D$31,4,FALSE) | H21: =VLOOKUP(H18,'02_ZONAS'!$A$5:$D$31,4,FALSE)
C22: Puntaje (tope 100) | F22: =MIN(100,F20+F21) | G22: =MIN(100,G20+G21) | H22: =MIN(100,H20+H21)
C23: Banda | F23: =VLOOKUP(F22,$J$5:$K$9,2,TRUE) | G23: =VLOOKUP(G22,$J$5:$K$9,2,TRUE) | H23: =VLOOKUP(H22,$J$5:$K$9,2,TRUE)
C24: Negocio HORECA (Sí/No) | F24: Sí | G24: Sí | H24: Sí
C25: ¿MQL? (permiso + HORECA + ≥ 40) | F25: =IF(AND(F6=1,F24="Sí",F22>=40),"Sí","No") | G25: =IF(AND(G6=1,G24="Sí",G22>=40),"Sí","No") | H25: =IF(AND(H6=1,H24="Sí",H22>=40),"Sí","No")
C26: ¿Candidato a SQL? (MQL + pidió persona o propuesta) | F26: =IF(AND(F25="Sí",OR(F16=1,F15=1)),"Sí, lo acepta una persona","No") | G26: =IF(AND(G25="Sí",OR(G16=1,G15=1)),"Sí, lo acepta una persona","No") | H26: =IF(AND(H25="Sí",OR(H16=1,H15=1)),"Sí, lo acepta una persona","No")
C28: Lectura: con el mismo recorrido, el puntaje cambia solo por la comuna (A +10, B +6, C +3). Verificado en el prototipo el 10-10: 93, 89 y 86.

Sheet 02_ZONAS
A1: Prioridad geográfica por comuna
A2: Hipótesis del equipo a calibrar con ventas reales por comuna. Ejecutivas con nombres ficticios. Rutas de demostración.
A4: Comuna | B4: Zona | C4: Prioridad | D4: Puntos Engagement | E4: Potencial Financial (0–100) | F4: Ejecutiva de zona (ficticia) | G4: Ruta (demo) | J4: Prioridad | K4: Puntos | L4: Potencial | M4: Hipótesis
A5: Quilicura | B5: Zona Norte y Poniente | C5: C | D5: =VLOOKUP(C5,$J$5:$L$8,2,FALSE) | E5: =VLOOKUP(C5,$J$5:$L$8,3,FALSE) | F5: Camila Soto · Ejecutiva Zona Norte y Poniente | G5: Ruta Norte · martes y viernes | J5: A | K5: 10 | L5: 100 | M5: Alta densidad de hoteles y restaurantes de ticket alto; ruta de reparto existente.
A6: Huechuraba | B6: Zona Norte y Poniente | C6: B | D6: =VLOOKUP(C6,$J$5:$L$8,2,FALSE) | E6: =VLOOKUP(C6,$J$5:$L$8,3,FALSE) | F6: Camila Soto · Ejecutiva Zona Norte y Poniente | G6: Ruta Norte · martes y viernes | J6: B | K6: 6 | L6: 70 | M6: Alto volumen (hoteles de negocio, restaurantes, aeropuerto) con ticket medio.
A7: Vitacura | B7: Zona Oriente | C7: A | D7: =VLOOKUP(C7,$J$5:$L$8,2,FALSE) | E7: =VLOOKUP(C7,$J$5:$L$8,3,FALSE) | F7: Paula Díaz · Ejecutiva Zona Oriente | G7: Ruta Oriente · martes y jueves | J7: C | K7: 3 | L7: 40 | M7: Cobertura con menor frecuencia de ruta.
A8: Lo Barnechea | B8: Zona Oriente | C8: A | D8: =VLOOKUP(C8,$J$5:$L$8,2,FALSE) | E8: =VLOOKUP(C8,$J$5:$L$8,3,FALSE) | F8: Paula Díaz · Ejecutiva Zona Oriente | G8: Ruta Oriente · martes y jueves | J8: R | K8: 2 | L8: 30 | M8: Cobertura por confirmar (distribuidor o despacho).
A9: Pudahuel | B9: Zona Norte y Poniente | C9: B | D9: =VLOOKUP(C9,$J$5:$L$8,2,FALSE) | E9: =VLOOKUP(C9,$J$5:$L$8,3,FALSE) | F9: Camila Soto · Ejecutiva Zona Norte y Poniente | G9: Ruta Norte · martes y viernes
A10: Renca | B10: Zona Norte y Poniente | C10: C | D10: =VLOOKUP(C10,$J$5:$L$8,2,FALSE) | E10: =VLOOKUP(C10,$J$5:$L$8,3,FALSE) | F10: Camila Soto · Ejecutiva Zona Norte y Poniente | G10: Ruta Norte · martes y viernes
A11: Independencia | B11: Zona Centro | C11: C | D11: =VLOOKUP(C11,$J$5:$L$8,2,FALSE) | E11: =VLOOKUP(C11,$J$5:$L$8,3,FALSE) | F11: Andrés Rojas · Ejecutivo Zona Centro | G11: Ruta Centro · lunes, miércoles y viernes
A12: Recoleta | B12: Zona Centro | C12: C | D12: =VLOOKUP(C12,$J$5:$L$8,2,FALSE) | E12: =VLOOKUP(C12,$J$5:$L$8,3,FALSE) | F12: Andrés Rojas · Ejecutivo Zona Centro | G12: Ruta Centro · lunes, miércoles y viernes
A13: Providencia | B13: Zona Oriente | C13: A | D13: =VLOOKUP(C13,$J$5:$L$8,2,FALSE) | E13: =VLOOKUP(C13,$J$5:$L$8,3,FALSE) | F13: Paula Díaz · Ejecutiva Zona Oriente | G13: Ruta Oriente · martes y jueves
A14: Las Condes | B14: Zona Oriente | C14: A | D14: =VLOOKUP(C14,$J$5:$L$8,2,FALSE) | E14: =VLOOKUP(C14,$J$5:$L$8,3,FALSE) | F14: Paula Díaz · Ejecutiva Zona Oriente | G14: Ruta Oriente · martes y jueves
A15: Lo Prado | B15: Zona Norte y Poniente | C15: C | D15: =VLOOKUP(C15,$J$5:$L$8,2,FALSE) | E15: =VLOOKUP(C15,$J$5:$L$8,3,FALSE) | F15: Camila Soto · Ejecutiva Zona Norte y Poniente | G15: Ruta Norte · martes y viernes
A16: Quinta Normal | B16: Zona Centro | C16: C | D16: =VLOOKUP(C16,$J$5:$L$8,2,FALSE) | E16: =VLOOKUP(C16,$J$5:$L$8,3,FALSE) | F16: Andrés Rojas · Ejecutivo Zona Centro | G16: Ruta Centro · lunes, miércoles y viernes
A17: Estación Central | B17: Zona Centro | C17: C | D17: =VLOOKUP(C17,$J$5:$L$8,2,FALSE) | E17: =VLOOKUP(C17,$J$5:$L$8,3,FALSE) | F17: Andrés Rojas · Ejecutivo Zona Centro | G17: Ruta Centro · lunes, miércoles y viernes
A18: Santiago Centro | B18: Zona Centro | C18: B | D18: =VLOOKUP(C18,$J$5:$L$8,2,FALSE) | E18: =VLOOKUP(C18,$J$5:$L$8,3,FALSE) | F18: Andrés Rojas · Ejecutivo Zona Centro | G18: Ruta Centro · lunes, miércoles y viernes
A19: Ñuñoa | B19: Zona Oriente | C19: B | D19: =VLOOKUP(C19,$J$5:$L$8,2,FALSE) | E19: =VLOOKUP(C19,$J$5:$L$8,3,FALSE) | F19: Paula Díaz · Ejecutiva Zona Oriente | G19: Ruta Oriente · martes y jueves
A20: La Reina | B20: Zona Oriente | C20: B | D20: =VLOOKUP(C20,$J$5:$L$8,2,FALSE) | E20: =VLOOKUP(C20,$J$5:$L$8,3,FALSE) | F20: Paula Díaz · Ejecutiva Zona Oriente | G20: Ruta Oriente · martes y jueves
... A31: Otra región | B31: Regiones | C31: R | D31: =VLOOKUP(C31,$J$5:$L$8,2,FALSE) | E31: =VLOOKUP(C31,$J$5:$L$8,3,FALSE) | F31: Valentina Mora · Ejecutiva Regiones (remota) | G31: Despacho por transporte · plazo por confirmar

Sheet 03_FINANCIAL
A1: Financial Score v0.1 · clientes con compras
A2: Pesos originales M2 (35/30/25/10) reescalados para dar 15 % a la zona. Cuentas, montos y pedidos FICTICIOS de demostración (los mismos del prototipo).
A4: Componente | B4: Peso | C4: Normalización (0–100)
A5: Ticket promedio | B5: 0.3 | C5: MIN(100; ticket / 5.000)
A6: Frecuencia | B6: 0.25 | C6: MIN(100; (pedidos en 180 días / 6) / 4 × 100)
A7: Margen relativo | B7: 0.2 | C7: Dato 0–100 (por confirmar con finanzas)
A8: Amplitud | B8: 0.1 | C8: MIN(100; categorías / 5 × 100)
A9: Zona | B9: 0.15 | C9: Potencial de la comuna (02_ZONAS)
A10: Suma de pesos (debe ser 100 %) | B10: =SUM(B5:B9)
A12: Cliente (ficticio) | B12: Tipo | C12: Comuna | D12: Ticket promedio (CLP, ficticio) | E12: Pedidos 180 días | F12: Margen relativo | G12: Categorías | H12: Ticket n | I12: Frecuencia n | J12: Margen n | K12: Amplitud n | L12: Zona n | M12: Financial (Excel) | N12: Financial (prototipo) | O12: Diferencia | P12: Tipo de cliente (prototipo)
A13: Hotel Altos del Parque | B13: Hotel | C13: Vitacura | D13: 432366 | E13: 13 | F13: 72 | G13: 4 | H13: =MIN(100,D13/5000) | I13: =MIN(100,(E13/6)/4*100) | J13: =F13 | K13: =MIN(100,G13/5*100) | L13: =VLOOKUP(C13,'02_ZONAS'!$A$5:$E$31,5,FALSE) | M13: =ROUND(H13*$B$5+I13*$B$6+J13*$B$7+K13*$B$8+L13*$B$9,0) | N13: 77 | O13: =M13-N13 | P13: Frecuente
A14: Restaurante Fogón 21 | B14: Restaurante | C14: Las Condes | D14: 270571 | E14: 19 | F14: 64 | G14: 3 | H14: =MIN(100,D14/5000) | I14: =MIN(100,(E14/6)/4*100) | J14: =F14 | K14: =MIN(100,G14/5*100) | L14: =VLOOKUP(C14,'02_ZONAS'!$A$5:$E$31,5,FALSE) | M14: =ROUND(H14*$B$5+I14*$B$6+J14*$B$7+K14*$B$8+L14*$B$9,0) | N14: 70 | O14: =M14-N14 | P14: Frecuente
A15: Café La Esquina Verde | B15: Cafetería | C15: Ñuñoa | D15: 176500 | E15: 25 | F15: 58 | G15: 4 | H15: =MIN(100,D15/5000) | I15: =MIN(100,(E15/6)/4*100) | J15: =F15 | K15: =MIN(100,G15/5*100) | L15: =VLOOKUP(C15,'02_ZONAS'!$A$5:$E$31,5,FALSE) | M15: =ROUND(H15*$B$5+I15*$B$6+J15*$B$7+K15*$B$8+L15*$B$9,0) | N15: 66 | O15: =M15-N15 | P15: Frecuente
A16: Hotel Plaza Moneda | B16: Hotel | C16: Santiago Centro | D16: 304318 | E16: 8 | F16: 55 | G16: 3 | H16: =MIN(100,D16/5000) | I16: =MIN(100,(E16/6)/4*100) | J16: =F16 | K16: =MIN(100,G16/5*100) | L16: =VLOOKUP(C16,'02_ZONAS'!$A$5:$E$31,5,FALSE) | M16: =ROUND(H16*$B$5+I16*$B$6+J16*$B$7+K16*$B$8+L16*$B$9,0) | N16: 54 | O16: =M16-N16 | P16: Frecuente
A17: Café Bistró Providencia | B17: Restaurante | C17: Providencia | D17: 146235 | E17: 12 | F17: 61 | G17: 2 | H17: =MIN(100,D17/5000) | I17: =MIN(100,(E17/6)/4*100) | J17: =F17 | K17: =MIN(100,G17/5*100) | L17: =VLOOKUP(C17,'02_ZONAS'!$A$5:$E$31,5,FALSE) | M17: =ROUND(H17*$B$5+I17*$B$6+J17*$B$7+K17*$B$8+L17*$B$9,0) | N17: 52 | O17: =M17-N17 | P17: Frecuente
A18: Bistró Los Aromos | B18: Restaurante | C18: La Reina | D18: 128300 | E18: 8 | F18: 52 | G18: 2 | H18: =MIN(100,D18/5000) | I18: =MIN(100,(E18/6)/4*100) | J18: =F18 | K18: =MIN(100,G18/5*100) | L18: =VLOOKUP(C18,'02_ZONAS'!$A$5:$E$31,5,FALSE) | M18: =ROUND(H18*$B$5+I18*$B$6+J18*$B$7+K18*$B$8+L18*$B$9,0) | N18: 41 | O18: =M18-N18 | P18: Frecuente
A19: Hotel Terminal Aéreo | B19: Hotel | C19: Pudahuel | D19: 378879 | E19: 16 | F19: 49 | G19: 3 | H19: =MIN(100,D19/5000) | I19: =MIN(100,(E19/6)/4*100) | J19: =F19 | K19: =MIN(100,G19/5*100) | L19: =VLOOKUP(C19,'02_ZONAS'!$A$5:$E$31,5,FALSE) | M19: =ROUND(H19*$B$5+I19*$B$6+J19*$B$7+K19*$B$8+L19*$B$9,0) | N19: 66 | O19: =M19-N19 | P19: Frecuente
A20: Cafetería Los Maitenes | B20: Cafetería | C20: Huechuraba | D20: 137364 | E20: 6 | F20: 57 | G20: 1 | H20: =MIN(100,D20/5000) | I20: =MIN(100,(E20/6)/4*100) | J20: =F20 | K20: =MIN(100,G20/5*100) | L20: =VLOOKUP(C20,'02_ZONAS'!$A$5:$E$31,5,FALSE) | M20: =ROUND(H20*$B$5+I20*$B$6+J20*$B$7+K20*$B$8+L20*$B$9,0) | N20: 38 | O20: =M20-N20 | P20: Frecuente
A21: Cafetería Plaza Poniente | B21: Cafetería | C21: Maipú | D21: 92615 | E21: 8 | F21: 44 | G21: 1 | H21: =MIN(100,D21/5000) | I21: =MIN(100,(E21/6)/4*100) | J21: =F21 | K21: =MIN(100,G21/5*100) | L21: =VLOOKUP(C21,'02_ZONAS'!$A$5:$E$31,5,FALSE) | M21: =ROUND(H21*$B$5+I21*$B$6+J21*$B$7+K21*$B$8+L21*$B$9,0) | N21: 31 | O21: =M21-N21 | P21: Frecuente
A22: Picada El Sur | B22: Restaurante | C22: La Florida | D22: 93500 | E22: 2 | F22: 40 | G22: 1 | H22: =MIN(100,D22/5000) | I22: =MIN(100,(E22/6)/4*100) | J22: =F22 | K22: =MIN(100,G22/5*100) | L22: =VLOOKUP(C22,'02_ZONAS'!$A$5:$E$31,5,FALSE) | M22: =ROUND(H22*$B$5+I22*$B$6+J22*$B$7+K22*$B$8+L22*$B$9,0) | N22: 24 | O22: =M22-N22 | P22: Inactivo
A23: Eventos Cordillera | B23: Eventos o catering | C23: Lo Barnechea | D23: 518667 | E23: 4 | F23: 68 | G23: 4 | H23: =MIN(100,D23/5000) | I23: =MIN(100,(E23/6)/4*100) | J23: =F23 | K23: =MIN(100,G23/5*100) | L23: =VLOOKUP(C23,'02_ZONAS'!$A$5:$E$31,5,FALSE) | M23: =ROUND(H23*$B$5+I23*$B$6+J23*$B$7+K23*$B$8+L23*$B$9,0) | N23: 71 | O23: =M23-N23 | P23: Ocasional
A24: Hostal Patio Recoleta | B24: Hotel | C24: Recoleta | D24: 70600 | E24: 5 | F24: 46 | G24: 1 | H24: =MIN(100,D24/5000) | I24: =MIN(100,(E24/6)/4*100) | J24: =F24 | K24: =MIN(100,G24/5*100) | L24: =VLOOKUP(C24,'02_ZONAS'!$A$5:$E$31,5,FALSE) | M24: =ROUND(H24*$B$5+I24*$B$6+J24*$B$7+K24*$B$8+L24*$B$9,0) | N24: 27 | O24: =M24-N24 | P24: Frecuente
... A32: Catering El Portal | B32: Eventos o catering | C32: San Miguel | D32: 97833 | E32: 5 | F32: 45 | G32: 1 | H32: =MIN(100,D32/5000) | I32: =MIN(100,(E32/6)/4*100) | J32: =F32 | K32: =MIN(100,G32/5*100) | L32: =VLOOKUP(C32,'02_ZONAS'!$A$5:$E$31,5,FALSE) | M32: =ROUND(H32*$B$5+I32*$B$6+J32*$B$7+K32*$B$8+L32*$B$9,0) | N32: 28 | O32: =M32-N32 | P32: Frecuente
A34: Tipo de cliente: Nuevo = primera compra en los últimos 90 días; Ocasional = 1 o 2 compras en 90 días; Frecuente = más de 2; Inactivo = sin compras en 90 días.

Sheet 04_KPIS
A1: KPIs comerciales, operacionales, de inbound y de experiencia
A2: Matriz propuesta. Ninguna cifra es resultado medido. Las metas académicas del caso se citan con su fuente [3]; el resto se fija tras levantar línea base.
A4: ID | B4: KPI | C4: Tipo | D4: Fórmula | E4: Unidad | F4: Ventana / período | G4: Fuente de datos | H4: Frecuencia | I4: Responsable | J4: Línea base | K4: Umbral o meta propuesta | L4: Decisión que apoya
A5: K01 | B5: Tasa de acceso Empresas | C5: Captación | D5: Clics únicos en Empresas / sesiones del inicio × 100 | E5: % | F5: Semanal | G5: Analítica web (eventos) | H5: Semanal | I5: Marketing | J5: [A LEVANTAR] | K5: Definir tras 4 semanas | L5: Ubicación y rótulo del acceso
A6: K02 | B6: Tasa de identificación | C6: Inbound | D6: Contactos con correo y permiso / sesiones que inician tus datos × 100 | E6: % | F6: Semanal | G6: Eventos del formulario + consentimiento | H6: Semanal | I6: Marketing | J6: [A LEVANTAR] | K6: Definir tras 4 semanas | L6: Campos y explicación de uso
A7: K03 | B7: Finalización del diagnóstico | C7: Activación | D7: Sesiones que terminan los 3 pasos y ven su propuesta / sesiones que iniciaron × 100 | E7: % | F7: Semanal | G7: Eventos del portal | H7: Semanal | I7: Marketing / UX | J7: [A LEVANTAR] | K7: Definir tras 4 semanas | L7: Orden y redacción de los pasos
A8: K04 | B8: Pedido de contacto humano | C8: Activación | D8: Contactos que solicitan revisión o propuesta por correo / propuestas vistas × 100 | E8: % | F8: Semanal | G8: CRM (R02) | H8: Semanal | I8: Ventas | J8: [A LEVANTAR] | K8: Definir tras 4 semanas | L8: Canal por defecto y disponibilidad
A9: K05 | B9: Primera respuesta humana en chat | C9: Servicio | D9: Mediana (primera respuesta de la ejecutiva − ingreso al chat), por zona | E9: min | F9: Diaria | G9: CRM (marcas de tiempo) | H9: Diaria | I9: Jefatura comercial | J9: [A LEVANTAR] | K9: ≤ 5 min (hipótesis del equipo) | L9: Dotación por zona y horario
A10: K06 | B10: Llamadas en plazo | C10: Servicio | D10: Llamadas realizadas dentro de la hora o del plazo informado / llamadas pedidas × 100 | E10: % | F10: Semanal | G10: CRM (cola de llamadas) | H10: Semanal | I10: Jefatura comercial | J10: [A LEVANTAR] | K10: Definir con capacidad real | L10: Reasignar entre zonas
A11: K07 | B11: Tasa MQL | C11: Calificación | D11: MQL / contactos identificados × 100, por zona | E11: % | F11: Mensual | G11: CRM + puntaje | H11: Mensual | I11: Marketing | J11: [A LEVANTAR] | K11: Definir tras calibrar | L11: Calibrar pesos y zonas
A12: K08 | B12: Tasa SQL | C12: Calificación | D12: SQL aceptados por una persona / MQL × 100, por zona | E12: % | F12: Mensual | G12: CRM | H12: Mensual | I12: Ventas | J12: [A LEVANTAR] | K12: Definir tras calibrar | L12: Calidad de leads por zona
A13: K09 | B13: Aceptación de propuesta | C13: Cierre | D13: Propuestas aceptadas / propuestas enviadas × 100; % ampliada | E13: % | F13: Mensual | G13: CRM (R08) | H13: Mensual | I13: Ventas | J13: [A LEVANTAR] | K13: Definir tras piloto | L13: Contenido de base y ampliada
A14: K10 | B14: Lead a cliente | C14: Cierre | D14: Clientes nuevos / leads de la cohorte × 100 | E14: % | F14: Trimestral (cohorte) | G14: CRM + ventas | H14: Mensual | I14: Gerencia comercial | J14: 12 % (supuesto académico [3]) | K14: 18 % (meta académica [3]) | L14: Escalar o ajustar el MVP
A15: K11 | B15: Reposición digital | C15: Recompra | D15: Reposiciones por canal digital / reposiciones totales × 100 | E15: % | F15: Mensual | G15: Pedidos + CRM | H15: Mensual | I15: Ejecutivos de cuenta | J15: 18 % (supuesto académico [3]) | K15: 40 % a 12 meses (meta académica [3]) | L15: Recompra en un toque y W7
... A36: K32 | B36: Reposiciones manuales | C36: Recompra | D36: Reposiciones pedidas por ejecutiva, correo o mensaje / reposiciones totales × 100 | E36: % | F36: Mensual | G36: CRM + pedidos | H36: Mensual | I36: Ejecutivos de cuenta | J36: 82 % (supuesto académico [3]) | K36: Bajarlo respecto del 82 % con la reposición en un toque | L36: W7, aviso por frecuencia y portal Mi cuenta

Sheet 05_WORKFLOWS
A1: Workflows de inbound automatizado
A2: Recorrido vigente19oct: C02 → C10 Productos → C11 Máquinas/condiciones → C03 Contacto → C04 Diagnóstico → C05 Propuesta → C06 Folio. W1 solo con correo y permiso; la cesta no crea consentimiento ni puntaje. Edición posterior exige nueva revisión; W4/W5 por correo y WhatsApp solo en postventa entrante.
A4: ID | B4: Nombre | C4: Segmento | D4: Etapa del funnel | E4: Gatillador (evento) | F4: Condición | G4: Espera | H4: Canal | I4: Acción y contenido | J4: Supresión / salida | K4: KPI | L4: Dónde se ve en el prototipo
A5: W1 | B5: Contacto nuevo | C5: Todos | D5: Identificación | E5: Tras explorar productos (C10) y máquinas (C11), deja datos con permiso (C03, antes del diagnóstico) | F5: Correo válido + permiso | G5: Inmediato | H5: Correo + CRM | I5: Correo con su N.º de seguimiento (la propuesta le llega al terminar, W2); ficha en el CRM; aviso a la ejecutiva | J5: — | K5: K02 | L5: C10/C11 preceden a C03; correo local y R01. Productos/cantidades y preferencia conservados hasta R02/R08.
A6: W2 | B6: Calificación y zona | C6: Por tipo de negocio y comuna | D6: Evaluación | E6: Marca su negocio y su comuna (C04, pasos 1 y 2) | F6: Comuna informada | G6: Inmediato | H6: Interno | I6: Suma puntaje (A +10, B +6, C +3, R +2); asigna ejecutiva de la zona; Logística revisa ruta; al terminar, el agente arma la propuesta y se la envía por correo | J6: — | K6: K07 | L6: R07 Agentes; R04
A7: W3 | B7: Propuesta aceptada o contacto humano | C7: Todos | D7: Activación | E7: Solicita revisión de su propuesta por correo (C05 → C06; si faltan datos, C03) | F7: Disponibilidad de la ejecutiva | G7: Inmediato | H7: Chat consultivo y correo comercial | I7: Solicitud registrada con folio, resumen y correo. La ejecutiva revisa condiciones y responde por correo; no confirma contrato ni instalación | J7: Sale cuando la ejecutiva responde (W6) | K7: K04, K05, K06, K09 | L7: C06; R02
A8: W4 | B8: Abandono con datos | C8: Con correo y permiso (dejó sus datos al principio) | D8: Evaluación | E8: Dejó sus datos y no terminó el diagnóstico, o vio su propuesta y no la aceptó ni pidió contacto | F8: Sin actividad ni atención humana activa; permiso por finalidad; recuperación solo por correo | G8: 24 h | H8: Correo + remarketing con permiso | I8: «Tu avance te espera» o «Tu propuesta te espera» con el video de su negocio (máx. 1); entra a la audiencia de remarketing (Google y Meta) con permiso | J8: Retoma, acepta o pasa a nutrición (W10) | K8: K03, K09 | L8: Simulado: aviso a los 2 min sin terminar (en la realidad, 24 h)
A9: W5 | B9: Propuesta sin respuesta | C9: SQL candidato | D9: Cierre | E9: Propuesta enviada por la ejecutiva (R02 o R08) | F9: Sin aceptación | G9: 72 h | H9: Correo | I9: Seguimiento de la ejecutiva con el resumen de su propuesta y los extras que marcó | J9: Acepta o cierra la secuencia | K9: K09 | L9: Diseñado (no simulado)
A10: W6 | B10: Toma humana | C10: Todos | D10: Activación / cierre | E10: La ejecutiva responde por correo | F10: — | G10: Inmediato | H10: — | I10: Pausa W4, W5 y respuestas autónomas de IA; conserva contexto y responsable para no duplicar mensajes | J10: — | K10: — | L10: R02 (pausa la ejecutiva simulada)
A11: W7 | B11: Recompra | C11: Cliente activo | D11: Recompra | E11: Días sin comprar ≥ su frecuencia habitual | F11: Sin incidencia crítica | G11: Según frecuencia del cliente | H11: Portal y correo; WhatsApp solo entrante | I11: Borrador del último pedido con cantidades y dirección; cliente revisa y confirma antes de crearlo; ejecutivo resuelve excepciones y Logística confirma ruta | J11: Repite pedido o contacto | K11: K11, K12 | L11: R01 Recompras; C09
A12: W8 | B12: Referidos | C12: Financial ≥ 70 | D12: Recompra | E12: Cliente frecuente y satisfecho | F12: Sin incidencia crítica | G12: — | H12: Portal | I12: Invitación con código de referido; beneficio lo aprueba jefatura | J12: Referido atribuido | K12: K15 | L12: C09; R07 aprobaciones
A13: W9 | B13: Incidencia crítica | C13: Cliente activo | D13: Postventa | E13: Ticket crítico abierto | F13: — | G13: Inmediato | H13: Portal/chat; WhatsApp postventa entrante | I13: Crea ticket con número, responsable y estado; pausa ampliación, campañas y referidos; traspasa a postventa con contexto | J13: Cliente confirma solución; si no, reabrir; baja de marketing se respeta | K13: K21 | L13: Recorrido demostrable; integración real propuesta en hoja 23
A14: W10 | B14: Nutrición por zona | C14: Puntaje < 40; zona A/B vs C/R | D14: Exploración | E14: Contacto identificado que no avanza | F14: Con permiso | G14: 3, 7 y 14 días | H14: Correo | I14: A/B: guía gráfica + video del caso + invitación al diagnóstico. C/R: guía + cobertura y despacho de su zona | J14: Pide contacto o se da de baja | K14: K03, K07 | L14: Diseñado (no simulado)

Sheet 06_CONTENIDOS
A1: Piezas audiovisuales y gráficas por etapa del funnel
A2: Estado al 10-10-2026. Solo se publican piezas con información verificable y autorizada por Marley Coffee.
A4: Pieza | B4: Formato | C4: Etapa | D4: Segmento | E4: Objetivo | F4: CTA | G4: Workflow | H4: Estado
A5: Video caso hotel (8 s) | B5: Audiovisual | C5: Exploración / espera | D5: Hotel, eventos | E5: Imaginar Marley Coffee en su operación | F5: Encontrar mi solución | G5: W3, W4 | H5: Producido para el MVP (Higgsfield)
A6: Video caso restaurante (8 s) | B6: Audiovisual | C6: Exploración / espera | D6: Restaurante, cafetería | E6: Imaginar el espresso de sobremesa con la marca | F6: Encontrar mi solución | G6: W3, W4 | H6: Producido para el MVP (Higgsfield)
A7: Experiencia de casos con scroll (C08) | B7: Audiovisual interactivo | C7: Evaluación | D7: Todos | E7: Comparar formatos por tipo de negocio | F7: Encontrar mi solución | G7: — | H7: Producido en el prototipo
A8: Fotos oficiales de producto | B8: Gráfico | C8: Evaluación | D8: Todos | E8: Mostrar el catálogo real sin precios | F8: Ver propuesta | G8: — | H8: Disponible (catálogo oficial)
A9: Correo con la propuesta y el N.º de seguimiento | B9: Texto + marca | C9: Identificación | D9: Todos | E9: Retomar sin repetir datos | F9: Volver a mi portal | G9: W1 | H9: Simulado en el prototipo
A10: Guía gráfica «Qué datos sirven para recomendarte» | B10: Gráfico | C10: Exploración | D10: Todos | E10: Bajar la duda antes del diagnóstico | F10: Empezar diagnóstico | G10: W10 | H10: Por producir
A11: Comparador visual grano / molido / cápsulas | B11: Gráfico | C11: Evaluación | D11: Por forma de servicio | E11: Elegir formato | F11: Ver mi recomendación | G11: W4 | H11: Por producir con datos aprobados
A12: Correo «Tu propuesta te espera» con video | B12: Audiovisual + texto | C12: Evaluación | D12: Puntaje ≥ 40 | E12: Recuperar a quien vio su propuesta y no la aceptó | F12: Aceptar mi propuesta | G12: W4 | H12: Por producir
A13: Clip para redes por zona (Oriente) | B13: Audiovisual | C13: Descubrimiento | D13: Zona A | E13: Atraer hoteles y restaurantes de alto ticket | F13: Empresas | G13: — | H13: Por producir
A14: Caso real HORECA | B14: Audiovisual / gráfico | C14: Evaluación | D14: Por tipo de negocio | E14: Prueba social verificable | F14: Encontrar mi solución | G14: — | H14: Pendiente de autorización de un cliente real
A16: ID | B16: Etapa del ciclo | C16: Táctica | D16: Público | E16: Acción | F16: Pieza | G16: Valor / CTA | H16: Evento y automatización | I16: Agente | J16: Indicador | K16: Medición | L16: Estado
A17: T01 | B17: Atraer | C17: SEO por intención profesional | D17: Administración de hoteles, restaurantes, cafeterías y eventos | E17: Crear /empresas y páginas útiles por negocio; enlazar desde Empresas, catálogo pertinente y guías. Explicar comodato y abastecimiento mensual con respuestas propias de cada operación. | F17: Páginas por negocio con una solución, comparador y preguntas frecuentes visibles. | G17: LM1 | H17: visita_empresas · W1 | I17: Marketing | J17: K01, K02 | K17: Impresiones y clics por intención; visitas a Empresas; contacto identificado. W1 solo al guardar datos con permiso. | L17: Arquitectura propuesta para producción: /empresas y destinos por intención. Las rutas hash del HTML local son navegación de demostración.
A18: T02 | B18: Atraer | C18: SEO técnico y estructura semántica | D18: Responsable que busca una máquina para su operación | E18: Validar rastreo e indexación; corregir la referencia genérica a MiTienda.com.br observada en robots.txt, publicar sitemap de URLs públicas correctas, canonical y metadatos únicos, un H1 descriptivo y enlaces rastreables. Diseñar páginas B2B indexables desde el servidor; no depender de rutas hash del prototipo. Excluir portal/CRM del índice y protegerlos con autenticación. | F18: Mapa de URLs públicas, sitemap y control en Search Console; datos estructurados fieles al contenido visible. | G18: LM1 | H18: visita_organica_empresas · W1 | I18: Marketing + TI | J18: K01 | K18: URLs indexables e indexadas, errores de cobertura y clics. La lectura del sitio del 15-10 confirma la referencia genérica en robots; cambios y rendimiento por validar con accesos reales. | L18: Táctica propuesta; publicación, accesos y resultados del piloto pendientes de validación.
A19: T03 | B19: Atraer | C19: SEM de búsqueda por intención | D19: Quien compara proveedores o modalidades para su negocio | E19: Separar intención de abastecimiento HORECA, equipos en comodato y café por negocio. Anuncio y destino explican el servicio real; excluir ofertas de venta/arriendo de equipos no disponibles. Medir términos y calidad de contactos, sin prometer posiciones ni rentabilidad. | F19: Tres grupos de búsqueda, anuncio por intención y destino por negocio/modalidad; etiquetas UTM. | G19: LM1 | H19: visita_campana_empresas · W1 | I19: Marketing + revisión comercial | J19: K01, K02, K08, K10 | K19: Clic, costo por contacto y SQL aceptado; comparar calidad por intención y zona. Sin presupuesto ni rentabilidad supuestos. | L19: Táctica propuesta; publicación, accesos y resultados del piloto pendientes de validación.
A20: T04 | B20: Atraer | C20: Orgánico útil en LinkedIn | D20: Administradores de hotel y responsables de alimentos y bebidas | E20: Publicar carrusel de planificación del café de desayuno: turnos, volumen aproximado, capacitación y reposición. Enlazar con UTM a guía y diagnóstico de hotel; ejemplos ilustrativos rotulados. | F20: Carrusel «Qué considerar para el café de tu hotel» y guía de datos necesarios. | G20: LM1, LM3 | H20: visita_linkedin_hotel · W1, W2 | I20: Marketing | J20: K01, K03, K07 | K20: Clic al activo, identificación, diagnóstico y MQL; no tratar alcance como venta. | L20: Táctica propuesta; publicación, accesos y resultados del piloto pendientes de validación.
A21: T05 | B21: Atraer | C21: Orgánico útil en Instagram | D21: Dueños de cafeterías/restaurantes y productores de eventos | E21: Crear clip de sobremesa o barra y carrusel grano/molido/cápsulas con criterios de elección; enlazar pieza por negocio mediante UTM. Mostrar productos oficiales e identificar escenas generadas como ilustrativas. | F21: Clip por negocio + comparador visual + destino relevante. | G21: LM1, LM3 | H21: visita_instagram_negocio · W1, W2 | I21: Marketing | J21: K01, K03 | K21: Guardados y clics al destino; finalización del diagnóstico por pieza y negocio. | L21: Táctica propuesta; publicación, accesos y resultados del piloto pendientes de validación.
A22: T06 | B22: Atraer | C22: Activaciones, alianzas y referidos | D22: Asistentes a activaciones y negocios invitados por clientes | E22: Vincular QR de una activación y código de referido con la página pertinente; ofrecer orientación útil. Publicar casos reales solo con autorización y evidencia, sin convertir escenas de ejemplo en testimonios. | F22: QR identificado, código referido y caso autorizado cuando exista. | G22: LM1, LM7 | H22: visita_activacion_o_referido · W8, W1 | I22: Marketing + Postventa | J22: K01, K15 | K22: Origen de activación o referido conservado hasta contacto/cliente. W8 nace del cliente que invita. | L22: Táctica propuesta; publicación, accesos y resultados del piloto pendientes de validación.
A23: T07 | B23: Interactuar | C23: Correo y diagnóstico conectados | D23: Contacto identificado por negocio, zona e intención | E23: Guardar datos con permiso, enviar número de seguimiento, conservar avance y construir propuesta al terminar; mostrar en CRM correo, canal, zona y variación del puntaje. | F23: Correo documental + diagnóstico de tres pasos + propuesta personalizada. | G23: LM2, LM3 | H23: contacto_identificado / diagnostico_terminado · W1, W2 | I23: Calificación + Ventas + Logística | J23: K02, K03, K07 | K23: Identificación, finalización y MQL; correo aceptado/clic si el proveedor lo confirma. | L23: Táctica propuesta; publicación, accesos y resultados del piloto pendientes de validación.
A24: T08 | B24: Interactuar | C24: Recuperación y nutrición por contexto | D24: Persona que dejó avance y no volvió | E24: W4 revisa inactividad a las 24 h y hace como máximo un aviso con la pieza de su negocio; W10 nutre a puntaje <40 con permiso a los 3, 7 y 14 días. Remarketing solo con permiso y exclusiones actualizadas. | F24: Correo «Tu avance/propuesta te espera», guía por zona y audiencia autorizada. | G24: LM2, LM3 | H24: inactividad_24h / nutricion_programada · W4, W10, W6 | I24: Marketing + Calificación | J24: K03, K07, K09 | K24: Avances retomados, propuesta aceptada y bajas; pausar recuperación al retomar o ser atendido. | L24: Táctica propuesta; publicación, accesos y resultados del piloto pendientes de validación.
A25: T09 | B25: Interactuar | C25: Conversación asistida y cierre humano | D25: Quien acepta, pregunta o compara extras | E25: IA explica recomendación y prepara resumen; la ejecutiva recibe conversación, propuesta y canal. Registrar respuesta y pausar IA/secuencias; revisar seguimiento a las 72 h solo si la propuesta sigue sin respuesta. | F25: Chat consultivo y correo con una ficha y responsable; propuesta base/ampliada. | G25: LM3, LM4 | H25: contacto_solicitado / propuesta_aceptada / respuesta_humana · W3, W5, W6 | I25: Ventas + ejecutiva | J25: K04, K05, K06, K08, K09, K10 | K25: Respuesta humana, SQL aceptado, aceptación y conversión; plazo de 5 min es hipótesis, no garantía. | L25: Táctica propuesta; publicación, accesos y resultados del piloto pendientes de validación.
A26: T10 | B26: Deleitar | C26: Reposición útil antes del quiebre | D26: Cliente activo con frecuencia conocida | E26: Preparar el último pedido según frecuencia; avisar por portal o correo. El cliente revisa y confirma; Logística valida ruta. WhatsApp solo si el cliente inicia postventa. | F26: Aviso de reposición + borrador en portal + seguimiento del pedido. | G26: LM5 | H26: frecuencia_cumplida / reposicion_confirmada · W7, W9 | I26: Postventa + Logística | J26: K11, K12, K16, K27 | K26: Reposición digital, frecuencia y entrega completa a tiempo; no enviar promoción si hay incidencia crítica. | L26: Táctica propuesta; publicación, accesos y resultados del piloto pendientes de validación.
A27: T11 | B27: Deleitar | C27: Servicio omnicanal con pausa comercial | D27: Cliente con problema en máquina, pedido o entrega | E27: Abrir ticket con número, adjuntos opcionales, criticidad y responsable; IA consulta estado y deriva con contexto; cliente confirma solución o reabre. Pausar ampliación y campañas. | F27: Portal/chat/WhatsApp entrante → ticket único → estado y confirmación. | G27: LM5 | H27: ticket_critico_abierto / incidencia_resuelta · W9, W6 | I27: Postventa + Logística + ejecutiva | J27: K21, K27 | K27: Primera respuesta y retención; estados verificables, sin prometer plazos no confirmados. | L27: Táctica propuesta; publicación, accesos y resultados del piloto pendientes de validación.
A28: T12 | B28: Deleitar | C28: Expansión y prueba social que alimentan la atracción | D28: Cliente satisfecho, sin incidencia crítica | E28: Recomendar tazas, material de marca o capacitación según operación; cliente elige. Invitar a referir si cumple Financial ≥70 y se aprueba beneficio; solicitar permiso antes de publicar su caso. | F28: Ampliación por necesidad, código de referido y caso documentado con permiso. | G28: LM4, LM6, LM7 | H28: interes_servicio / referido_atribuido · W8, W3 | I28: Postventa + Marketing + jefatura | J28: K13, K15, K27, K30, K31 | K28: Ticket, amplitud, margen y referidos convertidos; contrastar calidad de origen para mejorar atracción. | L28: Táctica propuesta; publicación, accesos y resultados del piloto pendientes de validación.
A30: Canal / táctica | B30: Segmento | C30: Intención o idea | D30: Destino o activo | E30: Ejemplo de pieza / estructura | F30: Valor y siguiente acción | G30: Evento y automatización | H30: Indicador | I30: Control
A31: SEO · T01/T02 | B31: Hoteles | C31: Máquina de café para hotel; café para desayuno y habitaciones | D31: /empresas/hoteles (URL propuesta) | E31: Título/H1 sobre café para hoteles; comparar Bar para desayuno y Pods para habitaciones; preguntas visibles sobre operación, sin tarifas inventadas. | F31: LM1: ver solución de su hotel → Ver mi solución | G31: visita_organica_empresas → contacto_identificado / W1; diagnóstico / W2 | H31: K01 visitas; K02 identificación; K07 MQL | I31: Publicar URL indexable, canonical y enlaces; validar sitemap/Search Console. No publicar el portal ni depender del hash local.
A32: SEO · T01/T02 | B32: Restaurantes | C32: Máquina de café para restaurante; café de sobremesa | D32: /empresas/restaurantes (URL propuesta) | E32: Contenido sobre servicio de sobremesa; comparar Pods sin barista y Bar con equipo; explicar comodato y abastecimiento mensual. | F32: LM1: comparación útil → Ver mi solución | G32: visita_organica_empresas → W1 al dejar datos; W2 al completar negocio/comuna | H32: K01, K02, K07 | I32: Vincular catálogo y guía; preguntas propias del negocio. No prometer posiciones ni resultados enriquecidos.
A33: SEO · T01/T02 | B33: Cafeterías | C33: Café en grano para cafetería; arriendo o compra de máquina profesional | D33: /empresas/cafeterias (URL propuesta) | E33: Página de barra, consumo y capacitación; explicar costo mensual frente a pago único, café y extras por separado. | F33: LM1/LM3: recomendación según operación → Ver propuesta | G33: visita_organica_empresas → W1/W2 → propuesta vista | H33: K01, K02, K07, K08 | I33: Producto y disponibilidad verificados para producción; rangos académicos no se publican como oferta real.
A34: SEO · T01/T02 | B34: Eventos y catering | C34: Coffee break para empresas; servicio de café para eventos | D34: /empresas/eventos (URL propuesta) | E34: Contenido sobre volumen, duración y servicio con barista o autoservicio; condiciones y cobertura por confirmar. | F34: LM1: imaginar el servicio → Ver mi solución | G34: visita_organica_empresas → W1/W2 | H34: K01, K02, K07 | I34: Casos y fotografías reales solo con evidencia y permiso; rotular recreaciones del prototipo.
A35: SEM · T03 | B35: Demanda de comodato | C35: Campaña Search Empresas / grupo Comodato | D35: /empresas/maquinas (URL propuesta; condiciones de comodato) | E35: Ejemplo propuesto: Café para tu negocio · equipo en comodato con compra mensual de insumos. Destino conecta catálogo y equipos antes de contacto. Términos por validar. | F35: LM1: comparador → Ver mi solución | G35: visita_campana_empresas con UTM → W1/W2 | H35: K01, K02, K07; costo por MQL y venta por levantar | I35: Presupuesto y puja sin definir. Revisar negativas de empleo, uso doméstico o búsquedas no atendibles antes de excluir; no anunciar beneficios no confirmados.
A36: SEM · T03 | B36: Demanda de abastecimiento | C36: Campaña Search Empresas / grupo Insumos | D36: /empresas/productos (URL propuesta; catálogo B2B) | E36: Ejemplo propuesto: Café e insumos para tu negocio · arma tu abastecimiento. Precio profesional y formatos sujetos a validación; no usar precio público B2C como tarifa mayorista. | F36: LM1/LM3: comparar modalidades → Ver propuesta | G36: visita_campana_empresas → W1/W2 → W3 al aceptar o pedir contacto | H36: K01, K02, K07, K09 | I36: Stock, precio y condiciones reales antes de activar. No usar los montos de demostración como oferta publicitaria.
A37: SEM · T03 | B37: Café y servicios HORECA | C37: Campaña Search Empresas / grupo Café HORECA | D37: Página del negocio correspondiente (URLs propuestas) | E37: Anuncio según hotel, restaurante, cafetería o evento; consulta y destino coherentes. Términos reales y negativas se revisan en el piloto. | F37: LM1: solución de su negocio → Diagnóstico breve | G37: visita_campana_empresas → W1/W2; venta confirmada al CRM y medición autorizada | H37: K01, K02, K07, K09; atribución a venta por validar | I37: Data Manager se propone para conversiones posteriores; requiere acceso, acción de conversión y consentimiento. No se crea campaña ni gasto en esta entrega.
A38: Orgánico · LinkedIn · T04 | B38: Administración de hoteles/restaurantes | C38: Carrusel: «Qué revisar antes de elegir el café de tu local» | D38: Publicación con UTM a /empresas y página de negocio | E38: 5 láminas: operación, volumen, forma de servicio, modalidad y siguiente paso. Foto de producto oficial y escena demostrativa identificada. | F38: LM1: lista útil para comparar → Ver mi solución | G38: visita_social_empresas → W1 solo al dejar contacto con permiso | H38: K01 tráfico referido; K02; K07; guardados/interacciones como apoyo | I38: Contenido educativo, sin testimonios ni mejoras cuantificadas inventadas. Llevar cada pieza al destino correspondiente.
A39: Orgánico · Instagram · T05 | B39: Operadores de cafeterías y eventos | C39: Clip breve: café servido y máquina según el contexto | D39: Video por negocio con enlace/UTM a destino propuesto | E39: Ejemplo: 12–20 s de preparación, beneficio operativo claro y cierre de una acción. Un producto protagonista y texto legible sin sonido. | F39: LM1: visualizar experiencia → Comparar solución | G39: visita_social_empresas → W1/W2; consulta por chat conserva referencia | H39: K01, K02, K07; reproducción y guardados como apoyo | I39: Mostrar equipo coherente; piezas de recreación se identifican. No presentar escenas generadas como clientes o casos de éxito reales.

Sheet 07_TEST_PLAN
A1: Plan de test de usabilidad (ronda 1 realizada el 15-10-2026)
A2: Test moderado, pensando en voz alta, dentro del prototipo («Iniciar test»). Ronda 1: 5 participantes con código (sin nombres): P1 computador, P2 y P3 celular en el sitio (T1, con las palabras de su negocio); P4 computador (T7) y P5 celular (T9) en el CRM. Nielsen (2000) [23] recomienda 5 por ronda. Una tarea por persona: las demás quedan como recorrido de diseño. Registro automático de tiempo, toques, SEQ y SUS; mapa de calor. Ronda 2 con 2 o 3 personas después de los cambios v6 (hoja 22).
A4: ID | B4: Rol | C4: Tarea (se lee al participante) | D4: Pantallas | E4: Criterio de éxito | F4: Métricas | G4: Umbral | H4: Ronda 1 (15-10)
A5: T1 | B5: Cliente | C5: Tienes un hotel (o restaurante, cafetería, eventos) y quieres cambiar el café. Desde esta página, busca cómo pedir una propuesta para tu negocio. | D5: C01 → C02 (LM1) | E5: Llega a la propuesta sin ayuda | F5: Éxito, tiempo por etapa, toques, SEQ | G5: ≥ 80 % sin ayuda | H5: Medida: P1, P2 y P3
A6: T2 | B6: Cliente | C6: Deja tus datos, marca tu negocio y mira tu propuesta. No sabes cuántas tazas sirves al día. | D6: C03 → C04 → C05 (LM2, LM3) | E6: Deja sus datos, termina los 3 pasos y ve su propuesta | F6: Éxito, tiempo en los datos, toques, SEQ | G6: ≥ 80 %; datos ≤ 30 s; pasos ≤ 25 s y ≤ 8 toques | H6: Recorrido de diseño (dentro de T1)
A7: T3 | B7: Cliente | C7: Acepta tu propuesta o pide hablar con una persona, y cuéntale al moderador qué pasará después. | D7: C05 → C06 (LM4) | E7: Acepta o pide hablar sin que le vuelvan a pedir sus datos, y describe el siguiente paso | F7: Éxito, comprensión | G7: ≥ 80 % | H7: Recorrido de diseño (dentro de T1)
A8: T4 | B8: Cliente | C8: En tu portal, pregunta si tienen tazas con la marca. Después, cambia la forma de contacto por otra. | D8: C06 (LM4) | E8: Envía el mensaje y cambia de canal sin perder la conversación | F8: Éxito, errores, SEQ | G8: ≥ 80 % | H8: Recorrido de diseño (no medida)
A9: T5 | B9: Cliente | C9: Ajusta tu propuesta para que incluya tazas Marley Coffee y acéptala. | D9: C05 → C07 (LM4) | E9: Acepta la ampliada | F9: Éxito, tiempo en la propuesta | G9: ≥ 80 %; ≤ 30 s | H9: Recorrido de diseño (dentro de T1)
A10: T6 | B10: Cliente activo | C10: Ahora imagina que ya eres cliente de Marley Coffee. Pide lo mismo que la última vez. | D10: C09 (LM5) | E10: Usa «Repetir último pedido» | F10: Éxito, tiempo, clics | G10: ≥ 80 % | H10: Recorrido de diseño (no medida)
A11: T7 | B11: Ejecutiva | C11: Eres ejecutiva de Marley Coffee: ingresa al CRM con tu cuenta. Un cliente te está esperando en el chat. Atiéndelo y respóndele. | D11: R00 → R01 → R02 | E11: Toma la conversación y responde (o envía la propuesta sugerida) | F11: Éxito, tiempo, SEQ | G11: ≥ 80 %; ≤ 60 s | H11: Medida: P4
A12: T8 | B12: Ejecutiva | C12: Averigua cada cuánto compra el Hotel Mirador Andino y cuánto gasta en promedio. Dile la respuesta al moderador. | D12: R03 → R04 | E12: Responde frecuencia y ticket promedio | F12: Éxito, tiempo | G12: ≥ 80 % | H12: Recorrido de diseño (no medida)
A13: T9 | B13: Jefatura | C13: Eres jefatura: ingresa al CRM con tu cuenta. ¿Cuántos clientes están comprando y cuántos SQL hay? ¿Qué zona trae más MQL? Dile la respuesta al moderador. | D13: R00 → R05 / R06 | E13: Responde los tres datos | F13: Éxito, tiempo, SEQ | G13: ≥ 80 %; ≤ 45 s | H13: Medida: P5
A15: Severidad (Nielsen 1994 [22]): 0 no es problema · 1 cosmético · 2 menor · 3 mayor · 4 catástrofe (corregir antes de lanzar). Se califica por frecuencia, impacto y persistencia.
A17: Guion de moderación (25 a 40 min)
A18: 0. Participantes y equipos | C18: Ronda 1 (15-10-2026): P1 computador, P2 y P3 celular en el sitio (T1); P4 computador (T7) y P5 celular (T9) en el CRM. El perfil se elige al empezar y la tarea se cuenta con las palabras de su negocio. Moderador con la guía Guia_Test_Usabilidad.html y el servidor del kit (Iniciar_test.bat): sin el servidor solo queda el PDF (así pasó en la ronda 1).
A19: 1. Bienvenida (2 min) | C19: «Gracias por ayudarnos. Vamos a probar un sitio en construcción, no a ti: no hay respuestas correctas. Piensa en voz alta: cuéntanos qué miras, qué esperas y qué te confunde. Te grabaremos solo con tu permiso.» Firmar consentimiento (Instrumentos_Terreno/E_CONSENTIMIENTO).
A20: 2. Contexto (3 min) | C20: ¿Qué tipo de negocio tienes o administras? ¿Cómo compran hoy el café y cómo lo reponen? ¿Con quién hablan cuando necesitan algo del proveedor?
A21: 3. Tarea (5 a 10 min) | C21: Una tarea por persona. El prototipo la muestra tal cual (columna C) y mide el tiempo por etapa, los toques y los toques sin respuesta. No mostrar dónde tocar. Si pasan 2 minutos sin avance o pide ayuda, ofrecer una pista y marcar éxito 0,5. Al terminar pregunta el SEQ (1 a 7). El informe PDF trae los tiempos por etapa y el mapa de calor; los CSV van a 08_TEST_REGISTRO.
A22: 4. Cierre (5 min) | C22: Cuestionario SUS (09_SUS). Preguntas: ¿Qué fue lo más útil? ¿Qué te hizo dudar? ¿Preferirías chat, llamada o correo, y por qué? ¿Qué te faltó para decidir?
A23: 5. Después de la sesión | C23: Pasar cada fricción a 10_HALLAZGOS con frecuencia, impacto, persistencia y severidad 0–4. Separar cita textual, observación e interpretación. No completar con supuestos lo que no se observó.
A24: Equipo comercial (T7–T9) | C24: Con P1 en computador: abrir test_crm.html y seguir T7 a T9 igual. Preguntar al final: ¿qué dato te falta para atender mejor?
A25: Lead magnets | C25: Observar si el participante lee el recuadro «Lo que recibes» antes de cada paso (LM1 a LM5) y preguntar al final: ¿qué te hizo seguir? ¿Qué esperabas recibir? Registrar citas en 10_HALLAZGOS.

Sheet 08_TEST_REGISTRO
A1: Registro por participante y tarea · ronda 1 (15-10-2026)
A2: Éxito: 1 = sin ayuda · 0,5 = con ayuda · 0 = no logra. Tiempo en segundos. SEQ 1 (muy difícil) a 7 (muy fácil). Fuente: informes PDF del test integrado, 15-10-2026, 00:07 a 01:01. Participantes con código, sin nombres. En blanco = no registrado (sin el servidor del kit no se guardaron los CSV).
A4: Participante | B4: Perfil / rol | C4: Dispositivo | D4: Tarea | E4: Éxito (1 / 0,5 / 0) | F4: Tiempo (s) | G4: Pidió ayuda (1/0) | H4: SEQ (1–7) | I4: Toques | J4: Toques sin respuesta | K4: Primera acción (s) | L4: Hasta Empresas (s) | M4: Pausa más larga (s) | N4: Pantalla con más tiempo | O4: SUS | P4: Nota del moderador (resumen)
A5: P1 | B5: Cliente · Hotel | C5: Computador | D5: T1 | E5: 0.5 | F5: 230.6 | G5: 1 | H5: 5 | I5: 29 | J5: 0 | K5: 10.2 | L5: 10.2 | M5: 21.4 | N5: C03 (47,6 s) | O5: 60 | P5: Le gustó el sitio y cómo interactuaban los videos. Se perdió después del formulario y del primer cuestionario: quería elegir la modalidad antes de que le dieran la propuesta.
A6: P2 | B6: Cliente · Restaurante | C6: Celular | D6: T1 | E6: 0.5 | F6: 196.2 | G6: 1 | H6: 6 | I6: 31 | J6: 2 | K6: 12.2 | L6: 15.5 | M6: 15.5 | N6: C03 (44,4 s) | O6: 60 | P6: No encontraba el menú (necesitó ayuda). Al pasar de pantalla en celular la vista no subía. Al terminar no supo qué hacer: faltó un aviso de que llegaría la propuesta. Preguntas largas; «faltaba un botón que seleccionara todo». 3 escenas en la portada eran muchas.
A7: P3 | B7: Cliente · Cafetería | C7: Celular | D7: T1 | E7: 1 | F7: 186.5 | G7: 0 | H7: 6 | I7: 31 | J7: 3 | K7: 6.7 | L7: 9.3 | M7: 17.1 | N7: C07 (57,3 s) | O7: 65 | P7: No encontraba el menú. Pulsó la solución arriba y le hubiese gustado ver antes los productos. Pidió el +56 9 ya escrito. Esperar la «nueva propuesta» al ajustar le pareció una pérdida de tiempo. Los precios se notaban poco; los videos le dieron seguridad.
A8: P4 | B8: Equipo · Ventas | C8: Computador | D8: T7 | E8: 0 | F8: 127.5 | G8: 0 | H8: 2 | I8: 18 | J8: 9 | K8: 7.1 | M8: 7.5 | N8: R02 (74,4 s) | O8: 27.5 | P8: Encontró el CRM intuitivo, pero no pudo dar una solución: no veía lo que cotizó el cliente ni una propuesta sugerida. Botones sin jerarquía; chat demasiado pequeño; pidió un mini tutorial.
A9: P5 | B9: Equipo · Jefatura | C9: Celular | D9: T9 | E9: 1 | F9: 76 | G9: 0 | H9: 5 | I9: 15 | J9: 10 | K9: 2.7 | M9: 10.1 | N9: R05 (52 s) | O9: 52.5 | P9: El panel le pareció útil, pero sin funciones para interactuar, cruzar datos o ver detalle. Su usuario escrito no entró. Todas las tarjetas e indicadores tenían el mismo color, sin jerarquía.
A10: P6 | P10: Ronda 2 (completar)
A11: P7 | P11: Ronda 2 (completar)
A12: P8 | P12: Ronda 2 (completar)
A14: Tarea | B14: Perfil | C14: Intentos | D14: Éxito sin ayuda (%) | E14: Éxito total (%) | F14: Tiempo promedio (s) | G14: SEQ promedio | H14: Umbral de éxito | I14: ¿Cumple?
A15: T1 | B15: Clientes (sitio) | C15: =COUNTIFS($D$5:$D$12,A15,$E$5:$E$12,"<>") | D15: =IFERROR(COUNTIFS($D$5:$D$12,A15,$E$5:$E$12,1)/C15,"pendiente") | E15: =IFERROR(AVERAGEIFS($E$5:$E$12,$D$5:$D$12,A15),"pendiente") | F15: =IFERROR(AVERAGEIFS($F$5:$F$12,$D$5:$D$12,A15),"pendiente") | G15: =IFERROR(AVERAGEIFS($H$5:$H$12,$D$5:$D$12,A15),"pendiente") | H15: 0.8 | I15: =IF(C15=0,"pendiente",IF(D15>=H15,"Sí","No"))
A16: T7 | B16: Ventas (CRM) | C16: =COUNTIFS($D$5:$D$12,A16,$E$5:$E$12,"<>") | D16: =IFERROR(COUNTIFS($D$5:$D$12,A16,$E$5:$E$12,1)/C16,"pendiente") | E16: =IFERROR(AVERAGEIFS($E$5:$E$12,$D$5:$D$12,A16),"pendiente") | F16: =IFERROR(AVERAGEIFS($F$5:$F$12,$D$5:$D$12,A16),"pendiente") | G16: =IFERROR(AVERAGEIFS($H$5:$H$12,$D$5:$D$12,A16),"pendiente") | H16: 0.8 | I16: =IF(C16=0,"pendiente",IF(D16>=H16,"Sí","No"))
A17: T9 | B17: Jefatura (CRM) | C17: =COUNTIFS($D$5:$D$12,A17,$E$5:$E$12,"<>") | D17: =IFERROR(COUNTIFS($D$5:$D$12,A17,$E$5:$E$12,1)/C17,"pendiente") | E17: =IFERROR(AVERAGEIFS($E$5:$E$12,$D$5:$D$12,A17),"pendiente") | F17: =IFERROR(AVERAGEIFS($F$5:$F$12,$D$5:$D$12,A17),"pendiente") | G17: =IFERROR(AVERAGEIFS($H$5:$H$12,$D$5:$D$12,A17),"pendiente") | H17: 0.8 | I17: =IF(C17=0,"pendiente",IF(D17>=H17,"Sí","No"))
A19: Nota de lectura: son 5 personas y una tarea larga cada una; los números orientan, no son estadística. Lo que pesa es lo que se repite entre personas y coincide con su línea de tiempo. Severidad y cambios en las hojas 10 y 22.

Sheet 09_SUS
A1: System Usability Scale (SUS) · ronda 1 y ronda 2
A2: Puntaje SUS 0–100 registrado por el test integrado (misma fórmula de abajo) el 15-10-2026; promedio de referencia 68 (Sauro 2011 [24]). Las respuestas por ítem de la ronda 1 no se guardaron (test sin el servidor del kit): solo se informa el puntaje del PDF.
A4: Participante | B4: Perfil | C4: Dispositivo | D4: SUS (0–100) | E4: Lectura
A5: P1 | B5: Cliente · Hotel | C5: Computador | D5: 60 | E5: =IF(D5>=68,"Sobre el promedio de referencia","Bajo el promedio de referencia (68)")
A6: P2 | B6: Cliente · Restaurante | C6: Celular | D6: 60 | E6: =IF(D6>=68,"Sobre el promedio de referencia","Bajo el promedio de referencia (68)")
A7: P3 | B7: Cliente · Cafetería | C7: Celular | D7: 65 | E7: =IF(D7>=68,"Sobre el promedio de referencia","Bajo el promedio de referencia (68)")
A8: P4 | B8: Equipo · Ventas | C8: Computador | D8: 27.5 | E8: =IF(D8>=68,"Sobre el promedio de referencia","Bajo el promedio de referencia (68)")
A9: P5 | B9: Equipo · Jefatura | C9: Celular | D9: 52.5 | E9: =IF(D9>=68,"Sobre el promedio de referencia","Bajo el promedio de referencia (68)")
A10: Promedio | B10: Clientes (P1–P3) | D10: =AVERAGE(D5:D7) | E10: =IF(D10>=68,"Cumple (≥ 68)","No cumple (< 68)")
A11: Promedio | B11: Equipo (P4–P5) | D11: =AVERAGE(D8:D9) | E11: =IF(D11>=68,"Cumple (≥ 68)","No cumple (< 68)")
A13: Ronda 2 · respuestas por ítem (1 = muy en desacuerdo a 5 = muy de acuerdo). Puntaje = ((ítems impares − 1) + (5 − ítems pares)) × 2,5
A14: Participante | B14: Í1 | C14: Í2 | D14: Í3 | E14: Í4 | F14: Í5 | G14: Í6 | H14: Í7 | I14: Í8 | J14: Í9 | K14: Í10 | L14: SUS
A15: P6 | L15: =IF(COUNT(B15:K15)=10,((B15-1)+(5-C15)+(D15-1)+(5-E15)+(F15-1)+(5-G15)+(H15-1)+(5-I15)+(J15-1)+(5-K15))*2.5,"")
A16: P7 | L16: =IF(COUNT(B16:K16)=10,((B16-1)+(5-C16)+(D16-1)+(5-E16)+(F16-1)+(5-G16)+(H16-1)+(5-I16)+(J16-1)+(5-K16))*2.5,"")
A17: P8 | L17: =IF(COUNT(B17:K17)=10,((B17-1)+(5-C17)+(D17-1)+(5-E17)+(F17-1)+(5-G17)+(H17-1)+(5-I17)+(J17-1)+(5-K17))*2.5,"")
A19: N.º | B19: Ítem del cuestionario
A20: 1 | B20: Creo que me gustaría usar este sitio con frecuencia.
A21: 2 | B21: Encontré el sitio innecesariamente complejo.
A22: 3 | B22: Pensé que era fácil de usar.
A23: 4 | B23: Creo que necesitaría ayuda de una persona con conocimientos técnicos para usarlo.
A24: 5 | B24: Las funciones del sitio estaban bien integradas.
A25: 6 | B25: Pensé que había demasiada inconsistencia.
A26: 7 | B26: Imagino que la mayoría aprendería a usarlo muy rápido.
A27: 8 | B27: Lo encontré muy engorroso de usar.
A28: 9 | B28: Me sentí muy confiado al usarlo.
A29: 10 | B29: Necesité aprender muchas cosas antes de poder usarlo.

Sheet 10_HALLAZGOS
A1: Hallazgos, severidad y mejoras
A2: Ciclo 0: revisión interna del autor del proyecto (09 a 12-10-2026), registrada con citas; NO es un test con usuarios. Ciclo 1: test con 5 usuarios del 15-10-2026 (participantes con código), con la mejora aplicada en v6. Severidad: crítica = 4, alta = 3, media = 2 (Nielsen 1994 [22]).
A4: ID | B4: Ciclo | C4: Fecha | D4: Fuente de evidencia | E4: Pantalla / tarea | F4: Hallazgo (fricción) | G4: Evidencia (cita u observación) | H4: Frecuencia | I4: Impacto | J4: Persistencia | K4: Severidad (0–4) | L4: Mejora incorporada | M4: Versión | N4: Estado
A5: H01 | B5: 0 | C5: 10-10-2026 | D5: Revisión interna (autor) | E5: C07–C10 | F5: Tras las 4 preguntas venían varias etapas (recomendación, propuesta, solicitud) que se leían como pestañas | G5: «después de las cuatro preguntas vienen hartas fases, como pestañas, que siento que son más fricciones» | H5: Alta | I5: Alto | J5: Alta | K5: 3 | L5: Contacto humano inmediato después de las preguntas (C05); lo demás pasa al portal | M5: v4 | N5: Incorporado; re-test con usuarios pendiente (T3)
A6: H02 | B6: 0 | C6: 10-10-2026 | D6: Revisión interna (autor) | E6: C05–C06 | F6: No se podía elegir hablar con una persona por chat real, llamada o correo | G6: Pidió llamada, correo o chat real en el portal, con un bot de bienvenida y espera según disponibilidad | H6: Alta | I6: Alto | J6: Alta | K6: 3 | L6: Omnicanal: chat real con bot y espera, llamada en cola o agendada, correo; cambio de canal sin perder la conversación | M6: v4 | N6: Incorporado; re-test pendiente (T3, T4)
A7: H03 | B7: 0 | C7: 10-10-2026 | D7: Revisión interna (autor) | E7: C04, CRM | F7: La geografía no pesaba en el puntaje ni en la asignación de ejecutiva | G7: «no es lo mismo un hotel o restaurante en las condes o providencia que en santiago centro» | H7: Alta | I7: Medio | J7: Alta | K7: 2 | L7: Comuna como pregunta 2; evento 14 en Engagement; 15 % en Financial; ejecutiva y ruta por zona; mapa R06 | M7: v4 | N7: Incorporado; calibrar con ventas por comuna
A8: H04 | B8: 0 | C8: 10-10-2026 | D8: Revisión interna (autor) | E8: CRM | F8: Menú del CRM demasiado largo (12 secciones) y centrado en el puntaje | G8: «tiene un menú gigante… ni yo mismo lo podría ocupar» | H8: Alta | I8: Alto | J8: Alta | K8: 3 | L8: Menú de 6 secciones por rol; puntaje como apoyo | M8: v4 | N8: Incorporado; re-test pendiente (T7–T9)
A9: H05 | B9: 0 | C9: 10-10-2026 | D9: Revisión interna (autor) | E9: R04 | F9: La ficha no mostraba qué compra el cliente ni con qué frecuencia | G9: Pidió ver qué compra, cuántas veces, primera compra, frecuencia y ticket promedio | H9: Alta | I9: Alto | J9: Alta | K9: 3 | L9: Ficha con datos de compra al frente y próxima mejor acción | M9: v4 | N9: Incorporado; re-test pendiente (T8)
A10: H06 | B10: 0 | C10: 10-10-2026 | D10: Revisión interna (autor) | E10: R05 | F10: El panel de jefatura no era agregado | G10: Pidió ver cuántos compran, MQL y SQL actuales y referidos, no a cada persona | H10: Media | I10: Medio | J10: Alta | K10: 2 | L10: Panel agregado por tipo de cliente y por zona, sin ranking por persona | M10: v4 | N10: Incorporado; re-test pendiente (T9)
A11: H07 | B11: 0 | C11: 10-10-2026 | D11: Revisión interna (autor) | E11: C02, C06, C08 | F11: Videos de casos con logos incorrectos, tazas sin marca y fuera del flujo | G11: «si en verdad vemos un video y no sale la marca bien… se ve como una inconsistencia» | H11: Alta | I11: Alto | J11: Alta | K11: 3 | L11: 2 videos nuevos desde fotos oficiales, revisados cuadro a cuadro, en C02, C06 y C08 de los 3 entregables | M11: v4 | N11: Incorporado
A12: H08 | B12: 0 | C12: 09-10-2026 | D12: Revisión interna (autor) | E12: Todo el sitio | F12: La marca aparecía como «Marley» sola | G12: «si pones solo marley, se puede mal entender. la marca es marley coffee» | H12: Media | I12: Medio | J12: Alta | K12: 2 | L12: Regla de marca en textos, etiquetas e informe; verificación automática | M12: v4 | N12: Incorporado; verificado 0 casos
A13: H09 | B13: 0 | C13: 09-10-2026 | D13: Revisión interna (autor) | E13: CRM | F13: El CRM se veía vacío en wireframes y mockups | G13: «sobre todo el crm que no había nada» | H13: Alta | I13: Alto | J13: Alta | K13: 3 | L13: Caso de ejemplo y datos de demostración rotulados en los tres entregables | M13: v3→v4 | N13: Incorporado
A14: H10 | B14: 0 | C14: 08-10-2026 | D14: Revisión interna (autor) | E14: Estados | F14: Estados en inglés incomprensibles («pending…») | G14: Vio una frase «pending…» que no entendía | H14: Media | I14: Medio | J14: Media | K14: 2 | L14: Todos los estados en español; verificación automática sin palabras en inglés | M14: v3→v4 | N14: Incorporado; verificado 0 casos
A15: H11 | B15: 0 | C15: 10-10-2026 | D15: Revisión interna (autor) | E15: C02–C09, CRM | F15: Los lead magnets LM1–LM7 no se veían en ninguna pantalla ni en el informe | G15: «ojo con los lead magnets que no los vi en ningún lado» | H15: Alta | I15: Alto | J15: Alta | K15: 3 | L15: LM visibles antes de cada esfuerzo (C02 a C09), adaptados al negocio; en el CRM (ficha, contexto, panel y marketing), diagramas, informe y hoja 15 | M15: v4.1 | N15: Incorporado; re-test pendiente (T1–T6)
A16: H12 | B16: 0 | C16: 12-10-2026 | D16: Revisión interna (autor) | E16: Informe | F16: El informe se leía técnico y pegado, sin hilo | G16: «el informe no es amigable… tengo una skill de informes que no usaste» | H16: Alta | I16: Alto | J16: Alta | K16: 3 | L16: Informe en HTML con el sistema visual de la skill: hilo narrativo, aire, una idea fuerte por párrafo y matrices en anexos | M16: 1.3 | N16: Incorporado
... A40: H36 | B40: 1 | C40: 15-10-2026 | D40: Test ronda 1 · P4 | E40: R02 · T7 | F40: El chat era chico y no había guía de uso | G40: P4: «el chat es demasiado pequeño» y pidió un mini tutorial | H40: 1 de 1 (ventas) | I40: Medio | J40: Media | K40: 2 | L40: Chat de 438 a 732 px de ancho (1366 × 900) y guía de 3 pasos que se cierra | M40: v6 | N40: Incorporado en v6
A43: Notas del observador (CSV de notas del test integrado). En la ronda 1 no se usaron notas en vivo (0 notas): las observaciones del moderador están resumidas en 08_TEST_REGISTRO (última columna). Completar en la ronda 2.
A44: Participante | B44: Dispositivo | C44: Tarea | D44: Minuto | E44: Tipo (duda / frase / gesto / error / idea) | F44: Nota del observador | G44: Pantalla | H44: Hallazgo asignado (ID)

Sheet 11_COMPARACION
A1: Comparación v3 → v4 → v5 y resultados contra umbrales
A2: Parte A: métricas de diseño verificadas en el código y en el navegador (no son datos de usuarios). Parte B: se completa sola desde 08 y 09 al registrar el test.
A4: Métrica de diseño | B4: v3 (09-10) | C4: v4 (10-10) | D4: v5 (12-10) | E4: Cómo se verificó
A5: Pantallas desde Empresas hasta elegir el canal humano (camino principal) | B5: 10 | C5: 8 | D5: 8 | E5: v5: C02, C03, 5 preguntas, C05; C05 muestra la solución preliminar antes del canal.
A6: Pantallas entre la última pregunta y la elección de contacto | B6: 2 | C6: 0 | D6: 0 | E6: v4 y v5: C05 justo después de la última pregunta.
A7: Canales humanos al terminar el diagnóstico | B7: Solo al final (C10) | C7: 3 inmediatos | D7: 3 + llamada en vivo con ficha | E7: C05 y C06; en v5 la ficha de la llamada se ve en el portal.
A8: Secciones en el menú del CRM | B8: 12 | C8: 6 | D8: 5 por rol (3 roles) | E8: Código del menú v3, v4 y D.ROLE_MENUS (v5).
A9: Puntajes que incorporan la geografía | B9: 0 de 2 | C9: 2 de 2 | D9: 2 de 2 | E9: Engagement (evento 14) y Financial (15 % zona).
A10: Clips con tazas y bolsas Marley Coffee legibles en todo el video | B10: 0 de 4 | C10: 2 de 2 | D10: 6 de 6 | E10: Revisión cuadro a cuadro (hojas de contacto de cada toma).
A11: Entregables con multimedia en su forma correcta | B11: 1 de 3 | C11: 3 de 3 | D11: 3 de 3 | E11: v5: prototipo con escenas al scroll; mockups con fotogramas; wireframes con cajas FOTO y VIDEO (prueba automática).
A12: Lead magnets con su promesa visible antes del esfuerzo (LM1–LM7) | B12: Parcial | C12: 7 de 7 | D12: 7 de 7 | E12: tests/qa_v4.py y tests/qa_v5.py.
A13: Errores de ejecución en todas las pantallas × 3 archivos (escritorio y celular) | B13: — | C13: 0 | D13: 0 | E13: v5: 25 rutas, tests/qa_v5.py, 12-10-2026.
A14: Fuentes oficiales de Marley Coffee cargadas (Festivo y GT Pressura) | B14: 0 de 2 | C14: 0 de 2 | D14: 2 de 2 | E14: document.fonts.check en la prueba automática.
A15: Amarillo de marca | B15: #F3C900 | C15: #F3C900 | D15: #F7BE00 (oficial) | E15: CSS oficial de marleycoffee.cl.
A16: Peso del HTML del prototipo | B16: — | C16: 7,5 MB | D16: 0,63 MB | E16: Multimedia en la carpeta recursos/ (build v5).
A17: Lighthouse de la landing (escritorio / celular, con gzip) | B17: — | C17: — | D17: 98–99 / 71 | E17: Lighthouse local 13-10-2026, versión final (mediana de cuatro corridas en celular: 68–74; la versión anterior medida en las mismas condiciones: 63–69); LCP 0,8 s / 3,6 s; TBT ~0,1 s / ~0,6 s; CLS 0.
A18: Máquinas oficiales para empresas con foto | B18: 0 | C18: 0 | D18: 4 | E18: Café al paso, Bar, Oficina y Pods (marleycoffee.cl/contactanos).
A19: Rangos de precio visibles (supuestos rotulados) | B19: Sin precios | C19: Sin precios | D19: 4 máquinas, café y 7 servicios | E19: Hoja 19; rótulo «Precio supuesto (académico)» en pantalla.
A20: Estados del portal del cliente | B20: 1 | C20: 1 | D20: 5 | E20: M4.portalState: registrado, en contacto, tu solución, propuesta y cliente.
A21: Datos estructurados (JSON-LD) en la landing | B21: 0 | C21: 0 | D21: 5 tipos | E21: Organization, Product ×4, Service ×2, FAQPage y BreadcrumbList.
A24: Parte B · Resultado del test (ronda 1, 15-10-2026) | B24: Umbral | C24: Resultado | D24: ¿Cumple? | E24: Fuente
A25: Éxito sin ayuda · sitio (T1, 3 clientes) | B25: 0.8 | C25: ='08_TEST_REGISTRO'!D15 | D25: =IF(ISNUMBER(C25),IF(C25>=B25,"Sí","No"),"pendiente") | E25: 08_TEST_REGISTRO
A26: Éxito sin ayuda · CRM (T7 y T9) | B26: 0.8 | C26: =AVERAGE('08_TEST_REGISTRO'!D16,'08_TEST_REGISTRO'!D17) | D26: =IF(ISNUMBER(C26),IF(C26>=B26,"Sí","No"),"pendiente") | E26: 08_TEST_REGISTRO
A27: SEQ promedio · sitio (T1) | B27: 5.5 | C27: ='08_TEST_REGISTRO'!G15 | D27: =IF(ISNUMBER(C27),IF(C27>=B27,"Sí","No"),"pendiente") | E27: 08_TEST_REGISTRO
A28: SEQ promedio · CRM (T7 y T9) | B28: 5.5 | C28: =AVERAGE('08_TEST_REGISTRO'!G16,'08_TEST_REGISTRO'!G17) | D28: =IF(ISNUMBER(C28),IF(C28>=B28,"Sí","No"),"pendiente") | E28: 08_TEST_REGISTRO
A29: SUS promedio · clientes | B29: 68 | C29: ='09_SUS'!D10 | D29: =IF(ISNUMBER(C29),IF(C29>=B29,"Sí","No"),"pendiente") | E29: 09_SUS
A30: SUS promedio · equipo | B30: 68 | C30: ='09_SUS'!D11 | D30: =IF(ISNUMBER(C30),IF(C30>=B30,"Sí","No"),"pendiente") | E30: 09_SUS
A31: Problemas de severidad 4 abiertos | B31: 0 | C31: =COUNTIFS('10_HALLAZGOS'!K5:K60,4,'10_HALLAZGOS'!N5:N60,"<>Incorporado*") | D31: =IF(ISNUMBER(C31),IF(C31<=B31,"Sí","No"),"pendiente") | E31: 10_HALLAZGOS
A34: Parte C · Cambio verificado después del test (v5 probado → v6.1) | B34: v5 (probado el 15-10) | C34: v6.1 (15-10) | D34: Cómo se verificó | E34: Hallazgo
A35: Datos que se piden antes del diagnóstico | B35: 4 campos (nombre, correo, celular y permiso), sin +56 9 | C35: Nombre y correo + permiso para guardar el avance; teléfono opcional. La comuna pasa al paso 2; recuperación por correo | D35: tests/qa_v5.py: C02 → C03 → C04 → C05; aviso de abandono programado | E35: H23
A36: Pasos del diagnóstico | B36: 5 preguntas, una por pantalla | C36: 3 pasos; el negocio se salta si ya se eligió y lo típico viene marcado | D36: qa_v5: «Paso 2 de 3» y valores sugeridos marcados | E36: H28
A37: Toques mínimos desde «Quiero esto en mi negocio» hasta ver el precio | B37: 15 (5 en el formulario y 10 en las preguntas) | C37: 8 (5 en los datos y 3 en los pasos: comuna, «Continuar» y «Ver mi propuesta») | D37: Conteo sobre el camino de qa_v5 | E37: H23, H28
A38: Espera para ver la propuesta ajustada | B38: 8 s de «nueva propuesta» (simulada) | C38: 0 s: se recalcula al instante | D38: M4.TM.proposal_after (v5) · setQuote (v6) | E38: H25
A39: Propuesta lista al terminar el diagnóstico | B39: No: la preparaba la ejecutiva | C39: Sí: la arma el agente de ventas al instante | D39: qa_v5: propuesta en estado «lista» en C05 | E39: H24, H25
A40: Momentos de la portada animada | B40: 3 (280 vh; 240 vh en celular) | C40: 2 (200 vh; 170 vh en celular), con la atención en vivo en una línea abajo | D40: CSS v6 y qa_v5 | E40: H27
A41: «Ver mi solución» antes de ver las máquinas | B41: Sí (portada, encabezado y barra fija) | C41: No: aparece después del carrusel de máquinas | D41: qa_v5: opacidad 0 e inactivo al inicio | E41: H26
A42: «MENÚ» y Empresas a la vista en la tienda (celular) | B42: Solo el ícono; Empresas dentro del menú | C42: «MENÚ» bajo el ícono y franja «¿Compras para tu negocio? Empresas →» | D42: qa_v5 en celular (390 × 844) | E42: H22
A43: La ejecutiva ve lo que cotizó el cliente junto al chat | B43: No | C43: Sí, en vivo, con la propuesta sugerida y «Enviar propuesta sugerida» | D43: qa_v5: R02 con lo cotizado y la tarjeta del agente | E43: H31
A44: Ancho del chat del CRM (1366 × 900) | B44: 438 px | C44: 732 px | D44: Medición en el navegador (15-10) | E44: H36
A45: Elementos con aspecto de botón que no respondían (CRM) | B45: Campana, tarjeta del cliente e indicadores | C45: Responden: avisos, ficha y detalle de cada indicador | D45: qa_v5 y tests/botones.py (clic real) | E45: H32
... A49: Puntaje de leads (tabla M2) | B49: 13 eventos + comuna | C49: Los mismos 13 eventos + comuna: cambia el momento, no los puntos | D49: qa_v5: eventos únicos, puntos de la tabla y tope 100 | E49: —

Sheet 12_SUPUESTOS
A1: Hipótesis, supuestos, trade-offs y próximos experimentos
A2: Las hipótesis H1 a H6 son las mismas del informe (si…, esperamos…, KPI y meta); «riesgo si es falso» dice qué pasa si no se cumple. Cada supuesto tiene la forma de validarlo. Los experimentos se ordenan por prioridad.
A4: ID | B4: Tipo | C4: Descripción | D4: Riesgo si es falso | E4: Cómo se valida / experimento | F4: Métrica | G4: Criterio de decisión | H4: Prioridad
A5: H1 | B5: Hipótesis | C5: Si el negocio deja tres datos al principio, con algo a cambio, y recibe su propuesta al instante, esperamos más contactos identificados, más propuestas aceptadas y recuperar a quien abandona. | D5: El sistema junta visitas y no contactos identificados, y quien abandona no se recupera. | E5: Ronda 2 (E1) y piloto. | F5: K02, K09 | G5: Identificación (K02) y aceptación (K09) [A LEVANTAR]; lead a cliente (K10) de 12 % a 18 %* en 12 meses. | H5: Alta
A6: H2 | B6: Hipótesis | C6: Si cada paso es un evento con su canal de origen, esperamos saber qué canal trae clientes, no solo visitas, y mover la inversión a lo que convierte. | D6: Se sigue invirtiendo sin saber qué canal trae clientes. | E6: Piloto y experimento de la landing (E6). | F6: K01, K10 | G6: Acceso a Empresas por canal (K01); costo por cliente −33 % al pasar de 12 % a 18 %* (hoja 16). | H6: Alta
A7: H3 | B7: Hipótesis | C7: Si el puntaje ordena la atención y la ejecutiva recibe el aviso a tiempo, esperamos atender primero a quien más vale, más rápido y con contexto. | D7: La ejecutiva atiende sin orden ni contexto y el lead que más vale espera igual que el resto. | E7: Ronda 2 (T7) y piloto. | F7: K05, K08 | G7: Primera respuesta (K05) ≤ 5 min; MQL a SQL (K08) [A LEVANTAR]. | H7: Alta
A8: H4 | B8: Hipótesis | C8: Si la propuesta recomienda productos y servicios según su rol y el stock, esperamos más categorías por cliente y un ticket más alto sin bajar el margen. | D8: La propuesta no sube las categorías por cliente ni el ticket. | E8: Piloto. | F8: K13, K30, K31 | G8: Ticket promedio (K13), amplitud (K30) y margen por cuenta (K31) [A LEVANTAR con el ERP]. | H8: Alta
A9: H5 | B9: Hipótesis | C9: Si reponer toma un toque, el aviso llega según la frecuencia y un KAM ve el historial, esperamos más clientes que reponen solos y se quedan. | D9: La reposición sigue siendo manual y la retención no se mueve. | E9: 12 meses de piloto. | F9: K11, K27 | G9: Reposición digital (K11) de 18 % a 40 %*; retención (K27) de 86 % a 90 %* (vida de 7,1 a 10 años). | H9: Alta
A10: H6 | B10: Hipótesis | C10: Si los agentes hacen lo repetible y una persona decide, esperamos más tiempo para vender y atender, y menos errores de logística. | D10: El equipo sigue haciendo a mano lo repetible y los errores de logística se mantienen. | E10: Piloto. | F10: K32, K16 | G10: Reposiciones manuales (K32) bajo el 82 %* actual; OTIF (K16) sobre su línea base de 92 %*. | H10: Alta
A11: S1 | B11: Supuesto | C11: Con la propuesta al instante, parte de los clientes acepta sin hablar con nadie y otros piden una persona: los dos caminos deben existir. | D11: Si casi nadie acepta solo, la propuesta no reemplaza la conversación; si nadie pide persona, sobra dotación. | E11: Ronda 2 y piloto: % que acepta directo vs % que pide hablar, y SQL de cada camino. | F11: K04, K09 | G11: Mantener los dos caminos; destacar el de mejor conversión. | H11: Alta
A12: S2 | B12: Supuesto | C12: La comuna es un buen indicador del potencial del local. | D12: Se prioriza mal y se descuidan buenos clientes de zonas C. | E12: Experimento E3: comparar ticket y conversión por zona durante 90 días. | F12: K08, K13 | G12: Recalibrar puntos A/B/C según datos. | H12: Alta
A13: S3 | B13: Supuesto | C13: Una ejecutiva puede responder el chat en pocos minutos en horario hábil. | D13: Esperas largas dañan la confianza. | E13: Piloto con registro de tiempos por zona. | F13: K05 | G13: Si la mediana > 5 min, sumar dotación o cambiar canal por defecto. | H13: Alta
A14: S4 | B14: Supuesto | C14: Existen rutas de despacho por zona con días fijos (dato de demostración). | D14: La propuesta promete fechas que no se cumplen. | E14: Validar con logística antes del piloto. | F14: K16, K17 | G14: No mostrar días de ruta hasta confirmarlos. | H14: Alta
A15: S5 | B15: Supuesto | C15: El cliente acepta indicar su comuna en el diagnóstico. | D15: Aumenta el abandono en el paso 2. | E15: Ronda 2 y embudo por paso. | F15: K03 | G15: Si cae la finalización, pedir la comuna junto a los datos. | H15: Media
... A32: E7 | B32: Experimento | C32: Orden de los lead magnets: el de servicio antes de los datos contra el de continuidad (LM2) antes de los datos. | D32: — | E32: Grupos alternados en la ronda 2 y en el piloto; el embudo por paso queda registrado en el CRM. | F32: K02, K03 | G32: Mantener el orden con más finalización del diagnóstico, siempre sin descuentos. | H32: 2

Sheet 13_GLOSARIO
A1: Glosario mínimo de métricas y definiciones
A2: Mismos criterios en informe, prototipo y anexos.
A4: Término | B4: Definición
A5: Lead | B5: Contacto que dejó sus datos y todavía no está calificado; en este MVP son los tres primeros campos del recorrido.
A6: Embudo de ventas | B6: El recorrido del cliente por etapas —lead, MQL, SQL, propuesta y cliente—; ordena la venta y dice en qué etapa está cada contacto.
A7: AARRR | B7: Marco para medir cada vuelta del flywheel: adquisición, activación, retención, referidos e ingresos. No ordena la venta: dice qué medir y qué probar.
A8: Flywheel | B8: Modelo de inbound en que atraer, interactuar y deleitar giran alrededor del cliente, y el promotor vuelve a atraer con sus referidos; el embudo vive adentro.
A9: SEO / SEM | B9: Búsqueda: SEO es aparecer sin pagar (Search Engine Optimization) y SEM es el anuncio pagado (Search Engine Marketing). Aquí la búsqueda se elige por intención de compra.
A10: UTM | B10: Etiqueta que se agrega al enlace para saber de qué canal, campaña o anuncio llegó cada visita (Urchin Tracking Module); es lo que permite atribuir cada peso en medios.
A11: KPI | B11: Indicador clave de desempeño: la cifra con la que se juzga si una acción funcionó. Cada KPI del informe lleva fuente, frecuencia y responsable (Anexo E, hoja 04).
A12: E-commerce | B12: Comercio electrónico: la compra y el pago en línea. Aquí, la parte asistida para empresas, que convive con los canales humanos.
A13: Blueprint | B13: Plano del inbound: la lámina que muestra el flywheel con su táctica, su pieza, su lead magnet, su workflow y su KPI por etapa (Anexo F).
A14: Mockups | B14: Pantallas del prototipo con la marca, las fotos oficiales y las escenas, tal como se ven en el sitio (Anexo C).
A15: Prompt | B15: Instrucción escrita que el equipo le da a una herramienta de inteligencia artificial; los prompts principales se declaran en el Anexo I del informe.
... A50: Toque sin respuesta | B50: Toque o clic en algo que no hace nada: señal de que la persona esperaba otra cosa.

Sheet 14_VERSIONES
A1: Versiones y nombres de archivos
A2: Los nombres coinciden con los archivos entregados.
A4: Versión | B4: Fecha | C4: Archivo | D4: Cambio principal
A5: 0.5 | B5: 08-10-2026 | C5: Informe_Primario_MVP_HORECA_Marley_Coffee.docx | D5: Informe primario previo al test (navegación y lenguaje).
A6: 0.6 | B6: 10-10-2026 | C6: Informe_Primario_MVP_HORECA_Marley_Coffee.docx | D6: Rediseño v4: contacto humano inmediato, geografía en los dos puntajes, CRM por rol.
A7: 1.0 | B7: 10-10-2026 | C7: Informe_EP3_MVP_HORECA_Marley_Coffee.pdf / .docx | D7: Reestructura según la pauta EP3 (apartados 1.1 a 1.7) y anexos auditables.
A8: 1.2 | B8: 10-10-2026 | C8: Informe_EP3_MVP_HORECA_Marley_Coffee.pdf / .docx | D8: Lead magnets, integración y capa agéntica en la cadena de valor, pago y facturación B2B, blueprint de inbound y trazabilidad de fuentes.
A9: v4 | B9: 10-10-2026 | C9: prototipo.html · mockups.html · wireframes.html | D9: Sitio Empresas C02–C09 y CRM R01–R09; videos de casos en los tres.
A10: v8 | B10: 10-10-2026 | C10: diagramas.html | D10: Flujos paralelos cliente · agentes · equipo; puntajes con geografía; menú del CRM.
A11: v4.1 | B11: 10-10-2026 | C11: prototipo.html · mockups.html · wireframes.html · test_sitio.html · test_crm.html | D11: Lead magnets LM1–LM7 visibles antes de cada esfuerzo y conectados al CRM.
A12: v9 | B12: 10-10-2026 | C12: diagramas.html | D12: Design Thinking, mapa del sitio, tareas críticas, matriz de lead magnets y carril LM en los flujos 1 y 2.
A13: 1.1 | B13: 10-10-2026 | C13: Anexo_E_Matrices_MVP_Marley_Coffee.xlsx | D13: Hoja 15 de lead magnets, H11 y protocolo de 3 o 4 participantes.
A14: v10 | B14: 10-10-2026 | C14: diagramas.html | D14: Capa agéntica e integración en la cadena de valor (flujo 5), sistemas y conexión, blueprint de inbound (flujo 6) y contenido segmentado.
A15: 1.2 | B15: 10-10-2026 | C15: Anexo_E_Matrices_MVP_Marley_Coffee.xlsx | D15: Este archivo: hojas 16 (economía unitaria), 17 (integración) y 18 (blueprint de inbound); KPIs K25–K29.
... A36: 3.2 | B36: 15-10-2026 | C36: Informe_EP3_MVP_HORECA_Marley_Coffee.pdf / .docx | D36: Informe con la propuesta al centro: vocabulario del caso, hipótesis con su KPI, decisiones de modalidades con fuente y anexos G a I; mismas matrices que el Anexo E 1.6.

Sheet 15_LEAD_MAGNETS
A1: Lead magnets LM1–LM7 · antes de cada esfuerzo
A2: Prompt del proyecto: lead magnets asociados al servicio, a su continuidad y a escalar la experiencia (accesorios, eventos, catering, activaciones, material POP, branding). Sin precios ni descuentos. Misma fuente que el prototipo.
A4: LM | B4: Nombre | C4: Promesa (texto en pantalla) | D4: Pantalla | E4: Aparece | F4: Qué recibe el cliente | G4: Qué obtiene Marley Coffee | H4: Señal / puntaje | I4: Agente | J4: Indicador para medirlo | K4: Siguiente paso
A5: LM1 | B5: Orientación | C5: Descubre qué solución Marley Coffee se adapta a tu negocio | D5: C02 | E5: Después de ver las máquinas, antes de pulsar «Ver mi solución» | F5: La máquina que te conviene, el café al mes y la ejecutiva de tu zona, en 1 minuto. | G5: Intención declarada y origen del contacto. | H5: Pulsa «Ver mi solución» (+10) | I5: Marketing | J5: Clics en «Ver mi solución» / visitas a Empresas | K5: C04
A6: LM2 | B6: Avance | C6: Recibe tu propuesta y tu número de seguimiento | D6: C03 | E6: Antes de dejar los datos, al empezar (antes del diagnóstico) | F6: Tu propuesta y un número de seguimiento en tu correo para retomar cuando quieras, sin repetir respuestas. | G6: Correo con permiso: contacto identificado. | H6: Formulario 1 (+20) | I6: Calificación | J6: Correos con permiso / visitas a C03 | K6: C06
A7: LM3 | B7: Configuración | C7: Configura el café de tu negocio | D7: C04 · C05 | E7: Antes del diagnóstico de 3 pasos | F7: Tu propuesta al instante: máquina, modalidad, café al mes, precio mensual estimado y la ruta de despacho de tu comuna. | G7: Datos para calificar: negocio, volumen, servicio, preferencias y comuna (zona). | H7: Diagnóstico y comuna (+24 a +32) | I7: Calificación y Orquestador | J7: Diagnósticos completos / diagnósticos iniciados | K7: C05
A8: LM4 | B8: Ampliación | C8: Descubre cómo ampliar la experiencia Marley Coffee | D8: C05 · C07 | E8: Junto a la propuesta, como recomendación apagada | F8: Extras recomendados para tu negocio: tazas de la marca, material para tu local, capacitación, eventos o catering. Solo entra lo que marcas. | G8: Venta cruzada: sube el ticket promedio. | H8: Recomendación (+8) y propuesta ampliada (+12) | I8: Ventas | J8: Prospectos que marcan interés o eligen la ampliada / propuestas enviadas | K8: SQL (lo acepta una persona)
A9: LM5 | B9: Reposición | C9: Repón en menos pasos y mantén continuidad | D9: C09 | E9: Antes de repetir el pedido | F9: Repetir el último pedido con un toque y un aviso antes de quedarte sin café, según tu consumo. | G9: Frecuencia de compra estable; menos clientes inactivos. | H9: Financial: frecuencia (25 %) | I9: Postventa y Logística | J9: Reposiciones digitales / reposiciones totales; avisos activados | K9: Pedido de reposición
A10: LM6 | B10: Expansión | C10: Escala tu experiencia Marley Coffee | D10: C09 | E10: Antes de pedir un servicio nuevo | F10: Eventos y catering con Marley Coffee, puntos de activación, material POP y branding, tazas y accesorios. | G10: Más categorías por cliente y ticket más alto. | H10: Financial: amplitud (10 %) y ticket (30 %) | I10: Postventa y Ventas | J10: Solicitudes de servicio / clientes activos | K10: Propuesta de servicio del ejecutivo de cuenta
A11: LM7 | B11: Referido | C11: Recomienda Marley Coffee con un beneficio experiencial | D11: C09 | E11: Antes de compartir su código | F11: Si otro negocio se suma con tu código, ambos reciben una experiencia de marca (cata para el equipo o material de marca), sujeta a aprobación. | G11: Nuevos contactos con origen «Referido». | H11: Origen: Referido | I11: Postventa y Marketing | J11: Contactos con origen «Referido» / clientes activos | K11: Nuevo contacto en el CRM
A13: Adaptación por tipo de negocio (LM3 cambia su texto; LM4 y LM6 ofrecen primero estos servicios)
A14: Negocio | C14: LM3 · lo que verá al terminar | F14: LM4 / LM6 · servicios que se ofrecen primero
A15: Hotel | C15: Bar para el desayuno, Pods en las habitaciones y tazas de la marca para el lobby | F15: Tazas y accesorios de la marca, Material de marca para tu local, Coffee Experience para eventos
A16: Restaurante | C16: espresso de sobremesa con grano o molido y la taza de la marca en cada mesa | F16: Tazas y accesorios de la marca, Material de marca para tu local, Catering con la marca
A17: Cafetería | C17: café en grano para la barra y variedad de preparaciones | F17: Capacitación de barista, Material de marca para tu local, Punto de activación
A18: Eventos o catering | C18: Coffee Experience con barra y barista, o Café al paso para volumen alto | F18: Punto de activación, Material de marca para tu local, Catering con la marca
A20: Servicios para ampliar y escalar (sin precios; condiciones las define la ejecutiva)
A21: accesorios | B21: Tazas y accesorios de la marca | C21: Taza mug negra y travel mug Marley Coffee para tu servicio.
A22: pop | B22: Material de marca para tu local | C22: Frente de barra, piso modular, exhibidor de bolsas y carta con la marca.
A23: evento | B23: Coffee Experience para eventos | C23: Barra Marley Coffee con barista, tazas y material de marca para tu evento.
A24: catering | B24: Catering con la marca | C24: Coffee break con mantel, tazas y café Marley Coffee para reuniones y lanzamientos.
A25: activacion | B25: Punto de activación | C25: Un módulo Marley Coffee con barista en tu local, hotel o centro comercial por una temporada.
A26: capacitacion | B26: Capacitación de barista | C26: Tu equipo aprende a preparar y cuidar la máquina con un barista de Marley Coffee.
A27: ocs | B27: Office Coffee Service | C27: Reposición programada, mantención de la máquina y soporte para tu operación.

Sheet 16_ECONOMIA_UNITARIA
A1: Economía unitaria con las metas del caso
A2: Celdas amarillas = supuestos académicos del caso [3] o datos por levantar. Celdas grises = fórmulas. Sin costos ni márgenes reales: no se inventan; las fórmulas quedan listas para el piloto.
A4: Concepto | B4: Hoy | C4: Meta / escenario | D4: Fórmula o fuente
A5: Retención anual HORECA | B5: 0.86 | C5: 0.9 | D5: Supuesto y meta académica del caso [3]
A6: Churn (tasa de cancelación) | B6: =1-B5 | C6: =1-C5 | D6: 1 − retención
A7: Vida esperada del cliente (años) | B7: =1/B6 | C7: =1/C6 | D7: 1 ÷ churn
A8: Cambio del LTV a igual contribución anual | C8: =C7/B7-1 | D8: LTV ≈ contribución anual × vida esperada
A9: Salida trimestral equivalente (regla 95-5) | B9: =1-B5^(1/4) | C9: =1-C5^(1/4) | D9: 1 − retención^(1/4): clientes que reconsideran proveedor cada trimestre
A10: Conversión lead → cliente | B10: 0.12 | C10: 0.18 | D10: Supuesto y meta académica del caso [3]
A11: Clientes por cada 100 leads | B11: =100*B10 | C11: =100*C10 | D11: 100 × conversión
A12: Cambio del CAC a igual costo por lead | C12: =B10/C10-1 | D12: CAC = costo por lead ÷ conversión
A13: Aumento de leads calificados | B13: 0 | C13: 0.25 | D13: Meta académica del caso [3]
A14: Clientes nuevos (base 100 leads hoy) | B14: =100*(1+B13)*B10 | C14: =100*(1+C13)*C10 | D14: leads × conversión
A15: NRR sin expansión (si el cliente perdido pesa como el promedio) | B15: =B5 | C15: =C5 | D15: ≈ retención
A16: Expansión necesaria para NRR = 100 % | B16: =1-B15 | C16: =1-C15 | D16: La deben aportar LM4 (ampliada), LM5 (frecuencia) y LM6 (servicios)
A17: Reposición digital (% de reposiciones) | B17: 0.18 | C17: 0.4 | D17: Supuesto y meta académica del caso [3]
A18: Contribución anual por cliente HORECA (CLP) | D18: Por levantar con finanzas (venta − costos variables, incluido despacho por zona)
A19: LTV (CLP) | B19: =IF(ISNUMBER(B18),B18*B7,"por levantar") | C19: =IF(ISNUMBER(C18),C18*C7,"por levantar") | D19: Contribución anual × vida esperada
A20: CAC (CLP) | D20: Por levantar: gasto de adquisición ÷ clientes nuevos atribuidos
A21: LTV / CAC (veces) | B21: =IF(AND(ISNUMBER(B19),ISNUMBER(B20)),B19/B20,"por levantar") | C21: =IF(AND(ISNUMBER(C19),ISNUMBER(C20)),C19/C20,"por levantar") | D21: LTV ÷ CAC
A22: Recupero de CAC (meses) | B22: =IF(AND(ISNUMBER(B18),ISNUMBER(B20)),B20/(B18/12),"por levantar") | C22: =IF(AND(ISNUMBER(C18),ISNUMBER(C20)),C20/(C18/12),"por levantar") | D22: CAC ÷ contribución mensual; considerar costos reales de equipo y servicio según la modalidad
A24: Lectura: retener 86 % → 90 % alarga la vida del cliente de 7,1 a 10 años (+40 % de LTV a igual margen); convertir 12 % → 18 % baja el CAC 33 % a igual costo por lead. Los valores en pesos se completan en el piloto (celdas amarillas vacías).

Sheet 17_INTEGRACION
A1: Integración: sistemas de Marley Coffee, contrato de llamadas y capa agéntica
A2: Stack observado en la auditoría técnica del equipo (ago. 2026: VTEX IO, Mercado Pago/Webpay, Connectif, VTEX Message Center, GTM, GA4, Blue Express) y sistemas del caso [3]. En el MVP las llamadas se simulan y se ven en el CRM (R07).
A4: Sistema | B4: Qué guarda o hace | C4: Evidencia | D4: Conexión | E4: Estado para el piloto | F4: Alternativa si no hay API
A5: CRM Marley Coffee Empresas (propuesto) | B5: Contactos, conversaciones, puntajes, propuestas y agentes | C5: Prototipo del MVP (Anexo A) | D5: Capa de integración propia: REST + webhooks | E5: Demostración local; servidor, identidad e integración real pendientes | F5: —
A6: VTEX IO (tienda actual) | B6: Catálogo, pedidos y logística; B2B Suite sujeto a habilitación | C6: Lectura del sitio 15-10-2026: generator VTEX y catálogo público HTTP 206; auditoría del equipo y VTEX Developers | D6: Catalog de lectura; Checkout para alta autorizada de pedidos; Orders Feed/Hook para estados; Logistics para inventario/cobertura | E6: Lectura de catálogo comprobada; acceso privado de escritura e inventario por validar | F6: Archivo programado (CSV/XLS) diario, como hoy envían datos los partners [3]
A7: ERP de Marley Coffee | B7: Facturación, inventario, pedidos y datos maestros | C7: Caso: 95 %* de transacciones completas, sin identificar el punto físico | D7: API del ERP; si no existe, conector intermedio o archivo programado | E7: Marca y API no informadas: por confirmar | F7: Archivo programado (CSV/XLS) diario, como hoy envían datos los partners [3]
A8: CRM comercial actual | B8: Cuentas B2B y oportunidades | C8: Caso: 65 %* de las cuentas; 40 %* de fichas completas | D8: Migración inicial y sincronización de cuentas | E8: Por confirmar | F8: Archivo programado (CSV/XLS) diario, como hoy envían datos los partners [3]
A9: Atención e incidencias | B9: Fallas de máquina, soporte y postventa | C9: Caso académico; auditoría externa detectó Zendesk en agosto, sin validar operación o cuenta interna | D9: API/webhooks del sistema confirmado; Zendesk ofrece mecanismos documentados si corresponde | E9: Sistema y accesos internos por validar | F9: Archivo programado (CSV/XLS) diario, como hoy envían datos los partners [3]
A10: Mercado Pago y Webpay | B10: Confirmación de transacción y conciliación | C10: Métodos reportados por la auditoría del equipo y documentación de proveedores; banner de Mercado Pago observado el 15-10-2026 | D10: Reutilizar integración autorizada de VTEX; confirmar estado con proveedor/servidor antes de conciliar | E10: Medios identificados por diagnóstico externo; configuración privada y acceso por confirmar | F10: —
A11: Facturación desde el ERP | B11: Factura y documentos de despacho | C11: Facturación indicada en el caso; referencia normativa SII no acredita una integración específica | D11: ERP o proveedor de facturación confirmado por Marley | E11: Emisión desde ERP o proveedor habilitado por confirmar; no se probó acceso | F11: —
A12: Rutas propias y transporte por definir | B12: Despacho y seguimiento | C12: Diseño previo del MVP; no acreditado como operador por la detección externa de «Blue» | D12: Proveedor y contrato por validar; Blue Express es una alternativa documentada, no una integración probada de Marley | E12: Operador y contrato por confirmar; detección externa de «Blue» no identifica Blue Express | F12: Archivo programado (CSV/XLS) diario, como hoy envían datos los partners [3]
A13: Connectif | B13: Automatización, contactos y personalización | C13: Pixel connectif.connectif presente en el HTML consultado el 15-10-2026; auditoría 27-08-2026 | D13: API de contactos, compras, productos y eventos personalizados documentada | E13: Recurso público observado; cuenta, permisos y automatizaciones por validar | F13: Archivo programado (CSV/XLS) diario, como hoy envían datos los partners [3]
A14: Google Tag Manager y GA4 | B14: Eventos, origen y medición del recorrido | C14: GTM y configuración sendGA4EventsValue visibles el 15-10-2026; auditoría externa de agosto | D14: dataLayer y Measurement Protocol desde servidor; eventos y consentimiento por validar en propiedad | E14: GTM/configuración pública observada; propiedad, permisos y recepción real de eventos por validar | F14: —
A15: Chat consultivo, correo comercial y WhatsApp postventa entrante | B15: Continuidad documental y conversacional | C15: Message Center para eventos de pedidos; política de WhatsApp y APIs de Connectif documentadas | D15: W1/W4 por correo mediante Connectif u orquestación. WhatsApp solo postventa entrante; Message Center no prueba nutrición comercial | E15: Flujos locales demostrables; remitente, número, permisos y proveedores pendientes | F15: Archivo programado (CSV/XLS) diario, como hoy envían datos los partners [3]
A17: Contrato de la capa de integración: cada acción de un agente es una llamada a un sistema
A18: Acción del agente | B18: Método | C18: Endpoint propio | D18: Sistema destino | E18: Qué hace / API del sistema | F18: Decide una persona
A19: Registrar origen | B19: POST | C19: /v1/contactos/{id}/eventos | D19: Google Tag Manager y GA4 | E19: Evento con UTM al CRM y a GA4 | F19: Según permiso y regla; operaciones críticas requieren aprobación
A20: Puntaje + | B20: PATCH | C20: /v1/contactos/{id}/puntaje | D20: CRM Marley Coffee Empresas (propuesto) | E20: Suma el evento al Engagement Score | F20: Según permiso y regla; operaciones críticas requieren aprobación
A21: Enviar correo de bienvenida | B21: POST | C21: /v1/mensajes/correo | D21: Chat consultivo, correo comercial y WhatsApp postventa entrante | E21: Plantilla de bienvenida con N.º de seguimiento | F21: Según permiso y regla; operaciones críticas requieren aprobación
A22: Enviar acuse por correo | B22: POST | C22: /v1/mensajes/correo | D22: Chat consultivo, correo comercial y WhatsApp postventa entrante | E22: Acuse con la ejecutiva asignada | F22: Según permiso y regla; operaciones críticas requieren aprobación
A23: Leer diagnóstico | B23: GET | C23: /v1/contactos/{id}/diagnostico | D23: CRM Marley Coffee Empresas (propuesto) | E23: Respuestas del diagnóstico de 3 pasos | F23: Según permiso y regla; operaciones críticas requieren aprobación
A24: Asignar ejecutiva de zona | B24: PATCH | C24: /v1/contactos/{id}/asignacion | D24: CRM comercial actual | E24: Ejecutiva por comuna; se sincroniza con el CRM comercial | F24: Según permiso y regla; operaciones críticas requieren aprobación
A25: Consultar ruta de despacho | B25: GET | C25: /v1/logistica/cobertura?comuna= | D25: VTEX IO (tienda actual) | E25: VTEX Logistics API: transportistas y cobertura | F25: Según permiso y regla; operaciones críticas requieren aprobación
A26: Estimar consumo | B26: GET | C26: /v1/contactos/{id}/diagnostico | D26: CRM Marley Coffee Empresas (propuesto) | E26: Volumen declarado | F26: Según permiso y regla; operaciones críticas requieren aprobación
A27: Elegir formato | B27: GET | C27: /v1/catalogo?formato= | D27: VTEX IO (tienda actual) | E27: VTEX Catalog API: productos oficiales | F27: Según permiso y regla; operaciones críticas requieren aprobación
A28: Pedir revisión de stock | B28: GET | C28: /v1/inventario?sku= | D28: VTEX IO (tienda actual) | E28: VTEX Logistics API: inventario por SKU | F28: Según permiso y regla; operaciones críticas requieren aprobación
A29: Consultar inventario | B29: GET | C29: /v1/inventario?sku= | D29: VTEX IO (tienda actual) | E29: VTEX Logistics API: inventario por SKU; ERP como respaldo | F29: Según permiso y regla; operaciones críticas requieren aprobación
... A51: Proponer referido | B51: POST | C51: /v1/aprobaciones | D51: CRM Marley Coffee Empresas (propuesto) | E51: Beneficio a revisión de jefatura | F51: Sí
A53: Capa agéntica por área de la cadena de valor
A54: Área | B54: Hoy (manual) * | C54: Agente | D54: Hace solo | E54: Decide una persona | F54: Sistemas | G54: KPI
A55: Captar | B55: Formulario de 8 campos sin respuesta inmediata; búsqueda B2B sin ruta propia | C55: Marketing | D55: Registra origen y eventos; nutre a quien no avanza (W10) | E55: Marketing aprueba campañas y piezas | F55: Google Tag Manager y GA4, Connectif, CRM Marley Coffee Empresas (propuesto) | G55: K01–K03
A56: Calificar | B56: CRM con 40 %* de fichas completas; sin puntaje ni zona | C56: Calificación y Orquestador | D56: Puntaje con zona; asigna la ejecutiva de la comuna | E56: La ejecutiva acepta el SQL | F56: CRM Marley Coffee Empresas (propuesto), CRM comercial actual | G56: K07, K08
A57: Vender | B57: Contacto por correo o teléfono sin contexto ni plazo | C57: Ventas (arma la propuesta al instante) y bot de bienvenida | D57: Arma la propuesta con catálogo y stock; le sugiere a la ejecutiva qué ofrecer | E57: La ejecutiva confirma el precio real, resuelve dudas y cierra | F57: Chat consultivo, correo comercial y WhatsApp postventa entrante, VTEX IO (tienda actual), CRM Marley Coffee Empresas (propuesto) | G57: K04, K05, K09
A58: Almacenar y preparar | B58: 82 %* de las reposiciones por ejecutivo, correo o mensajería | C58: Logística | D58: Consulta inventario, reserva stock y crea el pedido | E58: Logística confirma lo que no calza | F58: VTEX IO (tienda actual), ERP de Marley Coffee | G58: K11, K18, K19
A59: Distribuir | B59: 48 h en la RM y 72 a 96 h en regiones; OTIF 92 %* | C59: Logística | D59: Propone ruta y día según la comuna | E59: Una persona promete la fecha | F59: Rutas propias y transporte por definir, ERP de Marley Coffee | G59: K16, K17, K20
A60: Cobrar y facturar | B60: Checkout para personas: sin RUT, giro ni orden de compra | C60: Orquestador (avisa a Finanzas) | D60: Arma el alta con RUT y giro; emite la factura al despachar | E60: Finanzas valida la condición de pago vigente | F60: VTEX IO (tienda actual), Mercado Pago y Webpay, ERP de Marley Coffee, Facturación desde el ERP | G60: K25, K26
A61: Postventa y recompra | B61: Retención 86 %*; reclamos por falta de visibilidad del pedido y fallas | C61: Postventa | D61: Sugiere recompra por frecuencia, avisa (LM5) y propone referidos | E61: El ejecutivo de cuenta y la jefatura deciden | F61: Atención e incidencias, CRM Marley Coffee Empresas (propuesto), VTEX IO (tienda actual) | G61: K12, K15, K21, K27
A63: * Supuestos académicos del caso [3] y diagnóstico del equipo (ago. 2026). Las APIs de VTEX, Mercado Pago y Webpay están documentadas públicamente (developers.vtex.com, mercadopago.cl/developers, transbankdevelopers.cl; consulta 10-10-2026).

Sheet 18_BLUEPRINT_INBOUND
A1: Blueprint de inbound automatizado y contenido segmentado
A2: Etapa del funnel → segmento → pieza audiovisual o gráfica → lead magnet → canal → gatillador y workflow (hoja 05) → agente → KPI (hoja 04). Diagrama en el Anexo D (flujo 6).
A4: Flywheel | B4: Etapa del embudo | C4: Objetivo | D4: Segmento | E4: Pieza (audiovisual o gráfica) | F4: Lead magnet | G4: Canal | H4: Gatillador y workflow | I4: Agente | J4: KPI | K4: Puntaje que suma (acumulado)
A5: Atraer | B5: Descubrimiento | C5: Atraer intención profesional | D5: Tipo de negocio × zona | E5: Páginas Empresas por negocio con H1 y H2 por intención; contenido orgánico por tipo de negocio para Instagram y LinkedIn; anuncios de búsqueda por intención | F5: — | G5: SEO y Search Console, redes sociales orgánicas, SEM por intención y AEO | H5: Visita con UTM → registro de origen | I5: Marketing | J5: K01 | K5: 0 (solo origen UTM)
A6: Atraer | B6: Exploración | C6: Imaginar la solución en su local | D6: Por tipo de negocio | E6: Home con valor, proceso y productos (C02); catálogo cotizador (C10) → máquinas y comodato (C11) → contacto y diagnóstico. Casos como apoyo (C08). | F6: LM1 | G6: Sitio Empresas | H6: Exploración C10 → C11; sin puntos por artículos, cantidades ni permiso implícito. Iniciar cotización conserva el evento existente, sin duplicarlo. | I6: Marketing | J6: K01, K03 | K6: Evento de cotización existente +10 una sola vez; explorar/agregar productos no suma puntos adicionales.
A7: Interactuar | B7: Identificación | C7: Dejar contacto con permiso | D7: Todos | E7: Formulario al principio (nombre y correo, teléfono opcional y permiso); correo con N.º de seguimiento; si abandona, correo a las 24 h y remarketing autorizado | F7: LM2 | G7: Sitio y correo | H7: W1 al dejar correo con permiso; W4 si no termina en 24 h | I7: Calificación | J7: K02 | K7: +20 → 30 (identificado: correo con permiso)
A8: Interactuar | B8: Evaluación | C8: Recomendar y calificar | D8: Negocio × zona × banda de puntaje | E8: Diagnóstico de3capas; propuesta con equipo en comodato, selección de productos y consumo orientativo. Carga inicial y reposición por cotizar separadas; complementos opcionales. | F8: LM3 | G8: Sitio Empresas y remarketing (Google y Meta) | H8: W2 al ver la propuesta; W4 a las 24 h si no la acepta; W10 a los 3, 7 y 14 días | I8: Ventas (IA) y Calificación | J8: K03, K07 | K8: +5 +4 +10 +5 → 54 (MQL ≥ 40); +4 +4 → 62; ve su propuesta +8 → 70
A9: Interactuar | B9: Conversión | C9: Aceptar o hablar con una persona | D9: MQL por zona | E9: Revisar el resumen y solicitar propuesta por correo; el chat resuelve dudas y la ejecutiva confirma condiciones por correo | F9: LM4 | G9: Chat web y correo comercial | H9: W3 al aceptar o elegir canal; W5 a las 72 h; W6 pausa al responder | I9: Ventas (IA), ejecutiva y bot | J9: K04, K05, K08, K09 | K9: Acepta +15 o pide hablar +3 +12; portal +8 → 93; ampliada +12 → 100 (tope); SQL lo acepta una persona
A10: Deleitar | B10: Recompra y expansión | C10: Repetir y escalar | D10: Cliente activo por frecuencia | E10: Aviso de reposición; servicios con foto y rango (Coffee Experience, catering, POP, capacitación) | F10: LM5, LM6 | G10: Mi cuenta, correo y encuesta de satisfacción | H10: W7 según su frecuencia; W9 pausa ante incidencia | I10: Postventa y Logística | J10: K11, K12, K27 | K10: Financial: frecuencia 25 % y amplitud 10 %
A11: Deleitar | B11: Referido | C11: Recomendar | D11: Frecuente con Financial ≥ 70 | E11: Invitación con código y beneficio experiencial; tazas, POP y Coffee Experience para recordación | F11: LM7 | G11: Mi cuenta y activaciones de marca | H11: W8 cliente frecuente sin incidencia | I11: Postventa y Marketing | J11: K15 | K11: Origen «Referido»
A13: Contenido segmentado por tipo de negocio
A14: Negocio | B14: Exploración (pieza) | C14: Evaluación: LM3 muestra | D14: Conversión y expansión: LM4 / LM6 ofrecen primero | E14: Nutrición W10 (A/B: guía + video; C/R: guía + cobertura)
A15: Hotel | B15: Video caso hotel: desayuno, habitaciones y lobby | C15: Bar para el desayuno, Pods en las habitaciones y tazas de la marca para el lobby | D15: Tazas y accesorios de la marca, Material de marca para tu local, Coffee Experience para eventos | E15: Guía para el desayuno y las habitaciones
A16: Restaurante | B16: Video caso restaurante: espresso de sobremesa | C16: espresso de sobremesa con grano o molido y la taza de la marca en cada mesa | D16: Tazas y accesorios de la marca, Material de marca para tu local, Catering con la marca | E16: Guía del espresso de sobremesa
A17: Cafetería | B17: Escena cafetería (C08) y comparador de grano | C17: café en grano para la barra y variedad de preparaciones | D17: Capacitación de barista, Material de marca para tu local, Punto de activación | E17: Guía de barra con barista
A18: Eventos o catering | B18: Escena eventos (C08) y activación real con Hard Rock Café (2025) | C18: Coffee Experience con barra y barista, o Café al paso para volumen alto | D18: Punto de activación, Material de marca para tu local, Catering con la marca | E18: Guía de volumen alto en pocas horas
A20: Tácticas por etapa del flywheel (el inbound es un todo: cada etapa combina varias tácticas y cada una se mide)
A21: Etapa del flywheel | B21: Táctica | C21: Qué se hace | D21: Cómo se mide
A22: Atraer | B22: SEO desde el día cero | C22: Palabras clave definidas por buyer persona (gerente de A&B de hotel, dueño de restaurante o cafetería, productor de eventos): «café para empresas», «máquina de café para hotel», «máquina de café en comodato», «coffee break para empresas». Una página por intención con H1 y H2 que responden la búsqueda. | D22: Impresiones, clics y posición por consulta · K01
A23: Atraer | B23: Indexación con Google Search Console | C23: Verificar la propiedad /empresas, enviar un sitemap correcto (el actual tiene errores, hallazgo del diagnóstico), revisar cobertura e indexación, rendimiento por consulta y Core Web Vitals. | D23: Páginas indexadas y errores de cobertura
A24: Atraer | B24: Contenido orgánico en redes | C24: Instagram y LinkedIn por tipo de negocio: clips de cada escena (hotel, restaurante, cafetería, evento), casos y activaciones; cada pieza lleva UTM al sitio Empresas. | D24: Alcance, guardados y clics con UTM · K01
A25: Atraer | B25: SEM por intención profesional | C25: Búsqueda pagada con las mismas palabras clave, anuncios por tipo de negocio y página de destino por intención; palabras negativas para no pagar búsquedas de consumo personal (hoy el gasto se concentra en B2C, hallazgo). | D25: Costo por clic, costo por contacto y tasa a «Ver mi solución»
A26: Atraer | B26: AEO: respuestas para buscadores e IA | C26: Preguntas frecuentes con la respuesta primero y datos estructurados (FAQPage, Product, Organization) para que los buscadores y los asistentes de IA citen el sitio. | D26: Set fijo de preguntas medido por fecha
A27: Interactuar | B27: Correos automáticos y nutrición | C27: N.º de seguimiento al dejar su correo al principio (W1), propuesta por correo apenas el agente la arma (W2), aviso a las 24 h si abandona el diagnóstico o no acepta (W4) y nutrición a los 3, 7 y 14 días según negocio y zona (W10). | D27: Apertura, clics · K02, K03
A28: Interactuar | B28: Contenido personalizado | C28: Lo de su negocio y nada más: soluciones por momento del día, propuesta al instante con máquina, café al mes y precio, y extras recomendados para su tipo de negocio. | D28: Diagnóstico completo y MQL · K03, K07
A29: Interactuar | B29: Mensajes personalizados | C29: El chat web resuelve dudas y prepara el resumen. La ejecutiva recibe lo cotizado y responde por correo con las condiciones revisadas. | D29: Pedido de contacto y primera respuesta · K04, K05, K06
A30: Interactuar | B30: Remarketing | C30: Audiencias autorizadas de quienes dejaron el diagnóstico a medias (Google y Meta); recuperación por correo. Se pausa con atención humana activa (W6); sin WhatsApp comercial. | D30: Regreso al portal y diagnósticos retomados · K03
A31: Interactuar | B31: Activaciones en puntos | C31: Degustaciones y barra de marca en hoteles, restaurantes y eventos (como Hard Rock Café, 2025) con un código o QR al sitio Empresas. | D31: Contactos con origen «Activación»
A32: Interactuar | B32: Experiencia UX externa e interna | C32: Afuera: máquinas primero, datos básicos al principio para no perder a quien abandona, 3 pasos ya sugeridos, propuesta al instante y ajustes al instante. Adentro: CRM por rol con lo que cotizó el cliente y la propuesta sugerida por el agente. Validado con 5 usuarios (15-10) y por medir en una segunda ronda. | D32: Éxito de tarea, facilidad y SUS · K22, K23, K24
... A37: Deleitar | B37: Ramificación | C37: Sumar sucursales y servicios (LM6: eventos, catering, activaciones) y casos con permiso que vuelven a atraer: el ciclo se acelera. | D37: Ticket y NRR · K13, K27

Sheet 19_PRECIOS_SUPUESTOS
A1: Comodato: carga inicial confirmada y consumo orientativo
A2: Actualización19oct2026: correo y presupuesto del ejecutivo aportados por Carlos Vargas. No existe oferta de compra/arriendo de máquina. Los cuatro tipos del sitio son referencias; el correo menciona tres modelos sin identificar. No hay tarifa mensual ni mínimo confirmados.
A4: ID | B4: Máquina | C4: Tipo | D4: Para | E4: Tazas al día | F4: Formato | G4: Personal | H4: Régimen del equipo | I4: Disponibilidad | J4: Tarifa del equipo | K4: Validación
A5: bar | B5: Bar | C5: Espresso profesional con molinillo | D5: Cafetería, Restaurante, Hotel | E5: 100 a 400 tazas al día | F5: Café en grano | G5: Con barista (capacitación a confirmar) | H5: Comodato | I5: Modelo por confirmar | J5: No se ofrece venta/arriendo | K5: Ejecutiva valida
A6: oficina | B6: Oficina | C6: Superautomática con pantalla | D6: Hotel, Restaurante | E6: 40 a 150 tazas al día | F6: Café en grano y leche | G6: Autoservicio de un toque | H6: Comodato | I6: Modelo por confirmar | J6: No se ofrece venta/arriendo | K6: Ejecutiva valida
A7: cafe_al_paso | B7: Café al paso | C7: Automática de autoservicio | D7: Hotel, Eventos o catering | E7: 80 a 300 tazas al día | F7: Grano molido al momento y bebidas calientes | G7: Sin barista | H7: Comodato | I7: Modelo por confirmar | J7: No se ofrece venta/arriendo | K7: Ejecutiva valida
A8: pods | B8: Pods | C8: Espresso en dosis individuales, 2 tazas a la vez | D8: Restaurante, Hotel, Cafetería | E8: 30 a 120 tazas al día | F8: Pods (monodosis de café) | G8: Sin barista | H8: Comodato | I8: Modelo por confirmar | J8: No se ofrece venta/arriendo | K8: Ejecutiva valida
A10: Insumo | B10: Unidad | C10: Precio mín | D10: Precio máx | E10: Tazas por unidad | F10: Costo por taza mín | G10: Costo por taza máx | H10: Nota
A11: Café en grano para empresas (1 kg) | B11: kg | C11: Por cotizar | D11: Por cotizar | E11: 110 | F11: Por cotizar | G11: Por cotizar | H11: Rinde ~110 tazas por kilo (9 g por espresso, con merma).
A12: Pods de café (una por taza) | B12: pod | C12: Por cotizar | D12: Por cotizar | E12: 1 | F12: Por cotizar | G12: Por cotizar | H12: Una pod por taza.
A13: Bebidas calientes para Café al paso | B13: kg | C13: Por cotizar | D13: Por cotizar | E13: 60 | F13: Por cotizar | G13: Por cotizar | H13: Chocolate y leche en polvo; complementa al grano.
A15: Servicio | B15: Descripción | C15: Mín | D15: Máx | E15: Unidad | F15: Fuente
A16: Coffee Experience para eventos | B16: Barra Marley Coffee con barista, tazas y material de marca para tu evento. | C16: Por cotizar | D16: Por cotizar | E16: por evento (hasta 120 personas, 4 h) | F16: Servicio que Marley Coffee comunica en su LinkedIn
A17: Catering con la marca | B17: Coffee break con mantel, tazas y café Marley Coffee para reuniones y lanzamientos. | C17: Por cotizar | D17: Por cotizar | E17: por persona (mínimo 30) | F17: Supuesto académico
A18: Punto de activación | B18: Un módulo Marley Coffee con barista en tu local, hotel o centro comercial por una temporada. | C18: Por cotizar | D18: Por cotizar | E18: por mes | F18: Supuesto académico
A19: Material de marca para tu local | B19: Frente de barra, piso modular, exhibidor de bolsas y carta con la marca. | C19: Por cotizar | D19: Por cotizar | E19: por local (pago único) | F19: Supuesto académico
A20: Capacitación de barista | B20: Tu equipo aprende a preparar y cuidar la máquina con un barista de Marley Coffee. | C20: Por cotizar | D20: Por cotizar | E20: por sesión (hasta 6 personas) · condiciones por confirmar | F20: Supuesto académico
A21: Tazas y accesorios de la marca | B21: Taza mug negra y travel mug Marley Coffee para tu servicio. | C21: Por cotizar | D21: Por cotizar | E21: por taza (mínimo 24) | F21: Supuesto académico
A22: Office Coffee Service | B22: Reposición programada, mantención de la máquina y soporte para tu operación. | C22: A cotizar | D22: A cotizar | E22: servicio adicional a cotizar | F22: Servicio que Marley Coffee comunica en su LinkedIn
A24: Referencia pública (dato real) | B24: Mín | C24: Máx | D24: Fuente
A25: Café en grano 227 g | B25: 8574 | C25: 15590 | D25: Tienda pública marleycoffee.cl (API de catálogo VTEX), 12-10-2026
A26: Café molido 227 g | B26: 6894 | C26: 15590 | D26: Tienda pública marleycoffee.cl (API de catálogo VTEX), 12-10-2026
A28: Consumo orientativo y pago antes de instalar (magnitudes separadas)
A29: Máquina (ID) | B29: bar
A30: Tazas al día | B30: 250
A31: Días de servicio al mes | B31: 26
A32: Modalidad | B32: comodato
A33: Tazas por unidad de insumo | B33: =IF(B29="pods",E12,E11)
A34: Unidades al mes (kg o pods) | B34: =B30*B31/B33
A35: Reposición mensual · precio mínimo | B35: Por confirmar con el equipo
A36: Reposición mensual · precio máximo | B36: Por confirmar con el equipo
A37: Carga base de insumos · neto | B37: 1331220
A38: Kit de instalación · neto | B38: 100000
A39: Filtro · neto | B39: 60000
A40: Total antes de instalar · neto | B40: =SUM(B37:B39) -> 1491220
A41: Mínimo mensual de compra | B41: Por confirmar con el equipo
A42: Modelo disponible | B42: Por confirmar con el equipo
A43: Costo por taza mínimo | B43: Por confirmar con el equipo
A44: Costo por taza máximo | B44: Por confirmar con el equipo
A47: Modelo comercial confirmado
A48: Modalidad | B48: Estado | C48: Base | D48: Cómo se presenta
A49: Comodato | B49: Confirmado por correo del ejecutivo | C49: 19-10-2026 · correo y presupuesto aportados por Carlos Vargas | D49: Máquina prestada con compra mensual de insumos; carga base se paga antes de instalar.
A50: Abastecimiento mensual | B50: Precio, mínimo y formatos por confirmar | C50: No fueron detallados en la comunicación recibida | D50: Productos elegidos y cantidades son una solicitud para cotizar, no una compra ni un pedido confirmado.
A51: Cómo leer las cifras | B51: Montos netos CLP; referencia bajo/medio flujo | C51: Carga inicial:1.331.220 +100.000 +60.000 =1.491.220 | D51: La carga base no se repite automáticamente cada mes ni se recalcula desde el carrito. El consumo de250tazas/día ×26días /110tazas/kg =59,09kg/mes es supuesto operativo, no mínimo contractual.

Sheet 20_CRM_ROLES
A1: CRM por rol: cada rol ve lo que necesita para decidir
A2: R00 ingreso de trabajadores con usuario y contraseña. Las métricas generales (R05, R14, R15) son solo de la jefatura. Usuarios de demostración.
A4: Rol | B4: Usuario (demo) | C4: Pregunta que decide | D4: Inicio | E4: Menú (5 secciones) | F4: Qué ve | G4: Qué no ve
A5: Ventas | B5: Paula Díaz · Ejecutiva Zona Oriente | C5: A quién atender ahora y qué ofrecer | D5: R01 | E5: R01 Mi día · R02 Conversaciones y llamadas · R03 Mis clientes · R08 Cotizaciones · R10 Agenda | F5: Dónde está el cliente, qué compra, tipo de negocio, frecuencia, ticket, productos a sugerir, historial, cola de chats y llamadas, agenda y cotizaciones. | G5: Panel general, equipo y operación.
A6: Marketing | B6: Equipo de marketing · Contenido y campañas | C6: Qué contenido y a quién | D6: R11 | E6: R11 Flywheel e indicadores · R12 Leads y puntajes · R13 Contenido personalizado · R06 Mapa · R09 Reglas de puntaje | F6: Flywheel, MQL, SQL, puntajes, interacciones, lead magnets, origen y campañas, contenido personalizado por segmento y mapa. | G6: Panel general, equipo y operación.
A7: Jefatura | B7: Gerencia comercial · Vista general (solo jefatura) | C7: Dónde poner recursos y qué aprobar | D7: R05 | E7: R05 Panel general · R06 Zonas · R14 Equipo y tiempos · R15 Operación · R07 Agentes y aprobaciones | F7: Panel general (ventas, clientes activos, conversión, ticket, frecuencia, reposición digital, retención, OTIF), zonas, equipo y tiempos, operación, agentes y aprobaciones. | G7: —

Sheet 21_SEO_AEO
A1: SEO y AEO: títulos, datos estructurados e intenciones de búsqueda
A2: Prototipo académico con noindex. En producción se publicaría bajo marleycoffee.cl/empresas con estos títulos y datos estructurados.
A4: Pantalla | B4: Título (title) | C4: Descripción (meta description) | D4: Datos estructurados (JSON-LD)
A5: C02 | B5: Café para empresas, hoteles y restaurantes | Marley Coffee Empresas | C5: Máquinas de café en comodato con compra mensual de insumos, café orgánico y servicios para eventos. Recomendación en 1 minuto y ejecutiva de tu zona. | D5: Organization, Product (4 máquinas), Service (Coffee Experience, Office Coffee Service), FAQPage, BreadcrumbList
A6: C03 | B6: Tus datos para coordinar | Marley Coffee Empresas | C6: Deja tu nombre y correo para que una ejecutiva de tu zona revise tu propuesta de café para empresas. | D6: Organization, BreadcrumbList
A7: C04 | B7: Tu negocio en 3 pasos | Marley Coffee Empresas | C7: Tres pasos para recomendarte la máquina, el café y la ejecutiva de tu zona. | D7: Organization, BreadcrumbList
A8: C05 | B8: Tu propuesta de café para empresas | Marley Coffee Empresas | C8: Máquina sugerida, café al mes y precio mensual estimado al instante. Acéptala o habla con una ejecutiva de tu zona. | D8: Organization, BreadcrumbList
A9: C06 | B9: Mi portal | Marley Coffee Empresas | C9: Tu propuesta, los próximos pasos y la conversación con tu ejecutiva. | D9: Organization, BreadcrumbList
A10: C07 | B10: Ajusta tu propuesta de café | Marley Coffee Empresas | C10: Rangos de precio por tipo de máquina, consumo mensual estimado y servicios recomendados para tu negocio. | D10: Organization, Product (4 máquinas), BreadcrumbList
A11: C08 | B11: Casos: café en hoteles, restaurantes, cafeterías y eventos | Marley Coffee Empresas | C11: Recorre cómo se vive Marley Coffee en cada tipo de negocio. | D11: Organization, BreadcrumbList
A12: C09 | B12: Mi cuenta | Marley Coffee Empresas | C12: Repite tu pedido, programa avisos de reposición y pide servicios para tu negocio. | D12: Organization, BreadcrumbList
A14: Intención de búsqueda (no marca) | B14: Tipo | C14: Página destino | D14: Bloque que responde
A15: café para empresas | B15: Comercial | C15: C02 · H1 | D15: Hero y pestañas por negocio
A16: máquina de café para empresas | B16: Comercial | C16: C02 · Máquinas y C07 | D16: Las 4 barras con su ficha y el cotizador
... A22: cuánto cuesta una taza de café en un negocio | B22: Informativa (AEO) | C22: C02 · FAQ | D22: Respuesta primero: $180 a $390 por taza (supuesto)
A24: Mapa de encabezados por página (revisión 13-10 con el agente SEO de Agent OS: un H1 con la intención, H2 con la tarea o pregunta real, H3 con el detalle; la frase emocional queda como línea chica o párrafo)
A25: Página | B25: Nivel | C25: Antes | D25: Ahora | E25: Intención o consulta que cubre
A26: C02 (indexable) | B26: H1 | C26: El café de tu negocio, con una ejecutiva de tu zona | D26: Café para empresas: hoteles, restaurantes, cafeterías y eventos · El café de tu negocio, con una ejecutiva de tu zona | E26: café para empresas (comercial)
A27: C02 | B27: H2 | C27: De una taza a todo tu local | D27: Máquinas de café en comodato con compra mensual de insumos | E27: máquina en comodato y abastecimiento de café
A28: C02 | B28: H2 | C28: Así se ve en tu negocio | D28: Café para hoteles, restaurantes, cafeterías y eventos | E28: café para hoteles · restaurantes · cafeterías
A29: C02 | B29: H3 | C29: Del desayuno a la habitación, la misma taza (por pestaña) | D29: Café para hoteles / restaurantes / cafeterías · Barra de café para eventos (primera línea del H3) | E29: una intención por tipo de negocio
A30: C02 | B30: H2 | C30: Elige por cómo sirves, no por catálogo | D30: Máquinas de café para empresas: comodato con compra mensual de insumos | E30: máquina de café para empresas
A31: C02 | B31: H3 | C31: (nombres en negrita) | D31: Bar · Oficina · Café al paso · Pods (fichas de las 4 barras) | E31: entidades de producto (coinciden con Product)
A32: C02 | B32: H2 | C32: Más que café: experiencias con la marca | D32: Servicios de café para eventos y catering | E32: coffee break para empresas · barra de café para eventos
A33: C02 | B33: H2 / H3 | C33: Tres pasos, una persona (pasos en negrita) | D33: Cómo cotizar café para tu empresa · H3 por paso | E33: cómo cotizar café para empresas
A34: C02 | B34: H2 / H3 | C34: Lo que preguntan los negocios (preguntas sin título) | D34: Preguntas frecuentes sobre café para empresas · cada pregunta como H3 | E34: AEO: preguntas reales con respuesta primero
A35: C02 | B35: H2 | C35: ¿Lo imaginas en tu negocio? | D35: Cotiza el café de tu negocio en 1 minuto | E35: tarea: cotizar
A36: C07 (indexable) | B36: H1 / H2 | C36: Cotiza tu máquina por tipo de solución · 1 Máquina · 2 Modalidad · 3 Tu consumo · 4 Servicios | D36: Cotiza tu máquina de café para empresas · Elige la máquina de café · Arriendo o compra directa · Calcula tu consumo de café · Servicios para eventos y catering | E36: cotizar máquina de café (transaccional)
... A38: C03–C06, C09 (privadas, noindex) | B38: Estructura | C38: H2 antes del H1 (C03); salto H1 → H3 (C06, C09); promesas con nombre | D38: Un H1 primero, sin saltos de nivel; textos generales («una ejecutiva de tu zona») | E38: accesibilidad y orden de lectura
A40: FAQ con respuesta primero (FAQPage)
A41: ¿Puedo arrendar o comprar la máquina? | B41: La máquina se presta en comodato con compra mensual de insumos. La carga inicial de referencia para bajo/medio flujo es1.491.220CLP netos, antes de instalar. Modelo, formatos, compatibilidad, mínimo mensual y precios de reposición se confirman con el equipo; no se vende ni arrienda la máquina.
A42: ¿Qué máquina de café conviene para un hotel? | B42: Bar para el desayuno con barista, Pods para habitaciones o room service y Oficina para un buffet de autoservicio. La propuesta sale al instante con 3 pasos (tu negocio, tu local y cómo sirves).
A43: ¿Cuánto cuesta una taza de café para mi negocio? | B43: Entre $180 y $390 por taza según el formato: grano rinde unas 110 tazas por kilo y cada pod es una taza. Son precios supuestos para este prototipo.
A44: ¿Despachan café a empresas fuera de Santiago? | B44: Sí. En la Región Metropolitana el despacho va por ruta según la comuna; en regiones, por transporte, con plazo de 72 a 96 horas según el caso.
A45: ¿Puedo hablar con una persona antes de cotizar? | B45: Sí. El chat te orienta y la ejecutiva de tu zona responde por correo con tu diagnóstico para que no repitas nada.
A46: ¿Hacen eventos y catering con la marca Marley Coffee? | B46: Sí: Coffee Experience para eventos, catering con branding, puntos de activación y material POP para tu local.
A47: ¿El café Marley Coffee es orgánico? | B47: Parte del catálogo es orgánico certificado, como Keep On Moving en grano y molido.

Sheet 22_CAMBIOS_TEST
A1: Cambios después del test con usuarios (v5 → v6)
A2: Cada cambio sale de un problema observado el 15-10-2026 (participantes con código) y de las notas del moderador. La meta se mide en la ronda 2 con 2 o 3 personas. Fuente: análisis del test (6_TEST_USABILIDAD) y hojas 08 a 10.
A4: ID | B4: Pantalla | C4: Problema observado | D4: Evidencia | E4: Cambio aplicado en v6 | F4: Cómo se mide en la ronda 2 | G4: Meta | H4: Hallazgo | I4: Estado
A5: M01 | B5: C01 tienda | C5: Empresas escondida en el menú del celular | D5: 2 de 2 en celular no hallaron el menú (P2, P3) | E5: «MENÚ» bajo el ícono y franja «¿Compras para tu negocio? Empresas →» | F5: Segundos hasta Empresas en celular | G5: ≤ 10 s, sin ayuda | H5: H22 | I5: Aplicado
A6: M02 | B6: C02 → C03 | C6: El formulario era lento (44 a 50 s) | D6: Formulario: 44 a 50 s, ¼ del recorrido (P1, P2, P3) | E6: Formulario corto al principio (v6.1): 3 datos con +56 9 escrito y la comuna en el paso 2; sigue antes del diagnóstico para recuperar a quien abandona | F6: Tiempo en los datos y recorrido completo | G6: Datos ≤ 30 s; recorrido ≤ 150 s | H6: H23 | I6: Aplicado
A7: M03 | B7: C05 | C7: Modalidad y extras llegaban después de la propuesta | D7: P1 y P3 los querían antes | E7: Propuesta al instante con la modalidad elegible y extras recomendados apagados | F7: Personas perdidas entre la solución y la propuesta | G7: 0 | H7: H24 | I7: Aplicado
A8: M04 | B8: C06 | C8: No quedaba claro qué seguía | D8: P2 «se perdió en qué hacer» | E8: «¡Listo!» con quién escribe, por dónde, cuándo y 3 pasos | F8: «¿Y ahora qué?» en la ronda 2 | G8: 0 | H8: H25 | I8: Aplicado
A9: M05 | B9: C07 | C9: Espera de «nueva propuesta» y precios poco visibles | D9: P3: espera inútil; C07 57,3 s | E9: Ajustes al instante; precio mensual grande y en color | F9: Tiempo en la propuesta; precio encontrado sin ayuda | G9: ≤ 30 s; sí | H9: H25, H30 | I9: Aplicado
A10: M06 | B10: R02 conversación | C10: La ejecutiva no veía lo cotizado ni una propuesta sugerida | D10: P4 no logró T7 (facilidad 2, SUS 27,5) | E10: «Lo que cotizó el cliente» en vivo y tarjeta del agente con «Enviar propuesta sugerida» | F10: T7 sin ayuda y facilidad | G10: Logrado; facilidad ≥ 5 | H10: H31 | I10: Aplicado
A11: M07 | B11: CRM | C11: Botones sin jerarquía y toques que caían entre botones | D11: P4 y P5; toques entre «Llamar» y «Preparar propuesta» | E11: Principal en amarillo; secundarias con contorno; 44 px y 8 px de separación; la onda ya no agranda el botón | F11: Toques sin respuesta | G11: ≤ 10 % | H11: H32, H33 | I11: Aplicado
A12: M08 | B12: CRM | C12: Cosas con aspecto de botón que no hacían nada | D12: 19 de 33 toques sin respuesta (58 %) | E12: Campana con avisos, tarjeta que abre la ficha, indicadores con detalle | F12: Toques sin respuesta | G12: ≤ 10 % | H12: H32 | I12: Aplicado
A13: M09 | B13: R05 jefatura | C13: Panel sin jerarquía, sin detalle ni cruces; en celular se perdían los gráficos | D13: P5 tocó 10 indicadores en 11 s | E13: 3 indicadores principales con color, filtros de período y zona, detalle al tocar, gráficos y agentes en celular | F13: Tiempo de T9 y facilidad | G13: ≤ 45 s; facilidad ≥ 6 | H13: H33, H34 | I13: Aplicado
A14: M10 | B14: R00 ingreso | C14: El usuario escrito no entraba | D14: P5: 2 intentos, 24 s | E14: Sin distinguir mayúsculas, tildes, espacios ni dominio; cuentas de un toque | F14: Ingreso al primer intento | G14: ≤ 10 s | H14: H35 | I14: Aplicado
A15: M11 | B15: C02 Empresas | C15: Solución arriba, 3 escenas y tarjetas que no respondían | D15: P2 y P3 | E15: Máquinas primero, 2 momentos, «Ver mi solución» después de las máquinas, soluciones que se pueden tocar; cada negocio ve lo suyo | F15: Toques sin respuesta en C02 | G15: 0 | H15: H26, H27 | I15: Aplicado
... A21: M16 | B21: Ronda 2 | C21: Medir si los cambios funcionaron | D21: Sin medición no se sabe si mejoró | E21: Misma tarea con 2 o 3 personas y el kit con servidor | F21: Las metas de esta hoja | G21: Cumplir las metas | H21: — | I21: Próxima etapa (siguiente evaluación)

Sheet 23_CONVERSACION_POSTVENTA
A1: Un mismo acompañamiento: del primer mensaje a la postventa
A2: Propuesta de integración para el piloto; no envía mensajes reales. El chat conserva el contexto y la ejecutiva responde por correo. WhatsApp solo atiende postventa iniciada por el cliente.
A4: Momento | B4: Qué necesita la persona | C4: Datos mínimos | D4: Qué hace la IA | E4: Quién decide o responde | F4: Siguiente acción | G4: Recuperación / límite | H4: Pantallas
A5: Explorar y comparar | B5: Explorar productos y máquinas; entender comodato, carga inicial y reposición por cotizar. | C5: Negocio, comuna y consumo aproximado; contacto solo al guardar o pedir seguimiento | D5: Explica la recomendación con sus supuestos y conserva la selección | E5: Ejecutiva de zona revisa precio, cobertura y condiciones | F5: Ver propuesta; hablar con una persona | G5: Si falta dato o el modelo no sabe: reconocerlo y ofrecer traspaso | H5: C02–C07; R02; R04
A6: Contratar | B6: Ajustar y confirmar la propuesta | C6: Referencia de propuesta y cambios solicitados | D6: Prepara resumen de máquina, modalidad, consumo y extras elegidos | E6: Ejecutiva confirma la oferta y condiciones; cliente acepta expresamente | F6: Revisar resumen antes de aceptar | G6: Sin aceptación no hay contratación ni reserva definitiva | H6: C05–C06; R02; R08
A7: Instalar y comenzar | B7: Consultar entrega, instalación y capacitación | C7: Cuenta autenticada, sucursal y referencia de pedido | D7: Lee estado disponible en sistema, muestra fecha de actualización y registra consulta | E7: Logística o postventa confirma agenda y responsables | F7: Ver seguimiento; pedir ayuda | G7: Sin fecha confirmada: mostrar por confirmar y crear tarea | H7: C09; R02; R04; R10
A8: Reponer café | B8: Repetir un pedido con cambios opcionales | C8: Cuenta autenticada, sucursal, pedido anterior y cantidades | D8: Propone borrador con cantidades, precio disponible y dirección | E8: Ejecutiva valida excepciones; cliente confirma antes de generar pedido | F8: Revisar pedido; confirmar pedido | G8: Incidencia crítica: pausar venta y ofrecer atención; sin stock, sugerir alternativa sin imponer | H8: C09; R02; R04; R10
A9: Resolver un problema | B9: Máquina detenida, pedido incompleto o retraso | C9: Cuenta y sucursal, equipo o pedido, descripción; imagen opcional | D9: Clasifica, crea ticket y entrega número; no da instrucciones técnicas riesgosas | E9: Postventa toma el caso y coordina con servicio o logística | F9: Ver mi caso; hablar con postventa | G9: Fuera de horario: caso guardado y disponibilidad por confirmar; urgencia operativa se escala | H9: C09; R02; R04; R07
A10: Cerrar y acompañar | B10: Confirmar solución, evaluar atención y decidir próxima acción | C10: Ticket y confirmación del cliente; encuesta breve opcional | D10: Resume la solución y pregunta si quedó resuelto | E10: Responsable verifica cierre; si no está resuelto, reabre y conserva historial | F10: Sí, quedó resuelto; sigo con el problema | G10: Sin respuesta: seguimiento pendiente, no cierre automático; venta se reactiva tras resolución | H10: C09; R02; R04; R07
A12: Estado | B12: Cómo entra | C12: Qué ve la persona | D12: Control
A13: Asistente IA | B13: Inicio de conversación | C13: Identidad de IA visible, contexto y botón Hablar con una persona | D13: IA puede explicar y preparar; no confirmar compromisos comerciales
A14: Traspaso solicitado | B14: El cliente lo pide o la IA no puede resolver | C14: Resumen de intención, selección, gestiones, permiso y último mensaje | D14: IA pausa respuestas autónomas y se crea tarea asignable
A15: En espera de persona | B15: No hay responsable disponible | C15: Caso registrado y respuesta comercial por correo; disponibilidad por confirmar | D15: No simular ejecutivo conectado ni prometer plazo sin agenda real
A16: Atención humana | B16: Una persona toma la conversación en el CRM | C16: Nombre y rol del responsable; mismo historial y próximos pasos | D16: Bloqueo de doble respuesta IA/humano; la persona libera expresamente la atención
A17: Esperando cliente | B17: Se requiere aprobación o un dato | C17: Una pregunta o un resumen para confirmar; avance guardado | D17: No emitir pedido, cambiar dirección ni contratar sin confirmación
A18: Caso resuelto | B18: Solución registrada y confirmada | C18: Resultado, referencia y opción de reabrir | D18: Reactivar sugerencias comerciales solo cuando corresponda
A19: Baja de comunicaciones | B19: Solicitud de baja dentro o fuera del canal | C19: Confirmar baja y permitir atención iniciada por el cliente | D19: Suprimir mensajes proactivos según alcance solicitado y registrar fecha/finalidad
A21: Componente | B21: Diseño de la integración | C21: Fuente / estado
A22: Canal y alcance | B22: Correo para seguimiento comercial y chat web consultivo. WhatsApp Business Platform solo para postventa iniciada por el cliente; cuenta, proveedor y presupuesto por definir. El CRM conserva contexto y responsable. | C22: Propuesta técnica; no está conectada en esta demostración
A23: Entrada y entrega | B23: Un adaptador recibe eventos y estados de mensajes; registra el evento antes de procesarlo y vincula conversación, cuenta y ticket. Confirma entrega técnica solo si existe evento que la respalde. | C23: Propuesta de arquitectura a validar con documentación técnica y entorno de prueba de Meta
A24: Identidad y aislamiento | B24: No identificar una cuenta solo por teléfono. Verificar vínculo mediante acceso seguro al portal o método acordado; limitar consultas por cuenta, sucursal y rol. No pedir claves, documentos sensibles ni datos completos de tarjetas en el chat. | C24: Política WhatsApp, sección 3; diseño de seguridad propuesto
A25: Autenticación técnica | B25: Secretos únicamente en servidor; verificar autenticidad de notificaciones según documentación vigente, usar conexiones cifradas y permisos mínimos. El HTML no lleva claves ni credenciales. | C25: Diseño propuesto; configuración real pendiente
A26: Contrato de evento | B26: ID externo, conversación, cuenta interna verificada, intención, referencia de propuesta/pedido/ticket, fecha, canal, responsable y estado; permiso guardado por finalidad. Minimizar contenido y fijar retención antes del piloto. | C26: Contrato propuesto; sin datos personales reales en la entrega académica
A27: Idempotencia | B27: Deduplicar por identificador de evento y usar clave de operación para pedidos/tickets. Un evento repetido no crea dos pedidos ni dos casos; procesar estados fuera de orden sin retroceder indebidamente. | C27: Criterio técnico propuesto para CRM, ERP y adaptador
A28: Reintentos y fallos | B28: Cola de salida con reintento limitado y espera progresiva; si se agota, tarea visible para una persona. No marcar enviado cuando falló ni repetir el mismo mensaje al recuperar conexión. | C28: Parámetros y alertas por definir en el piloto
A29: Sistemas de negocio | B29: CRM conserva conversación, responsable y permiso; ERP o plataforma de pedidos confirma stock, precio y operación; sistema de tickets registra incidencia. Si no hay API, usar cola de revisión humana sin inventar confirmación. | C29: Disponibilidad de API y permisos de Marley Coffee por confirmar
A30: Permiso y baja | B30: El cliente inicia WhatsApp para postventa. Registrar finalidad, origen y retiro; una consulta de servicio no autoriza publicidad. El MVP no inicia mensajes ni campañas por este canal. Seguimiento comercial por correo autorizado. | C30: Política WhatsApp, sección 1 y buenas prácticas de consentimiento
A31: Ventana y plantilla | B31: Atender solo la postventa que inicia el cliente dentro de las condiciones vigentes del canal. El MVP no inicia ni reabre conversaciones de WhatsApp con plantillas. Si no puede continuar, registrar el caso y ofrecer seguimiento por correo. | C31: Política WhatsApp, sección 2; vigencia consultada 15-10-2026
A32: Control humano | B32: Escalamiento claro desde la IA a persona, teléfono, correo o soporte web. El cliente puede pedirlo en cualquier momento. Cambios de contrato, excepciones de precio, compensaciones y agenda definitiva requieren al responsable habilitado. | C32: Política WhatsApp, sección 2; reglas de negocio propuestas
... A34: Costos y disponibilidad | B34: Verificar tarifas vigentes, categoría de plantilla, disponibilidad del equipo y condiciones del servicio antes del piloto. No se fijan números telefónicos, proveedor, costo ni plazo de respuesta sin confirmación. | C34: Por definir con Marley Coffee; consulta oficial de precios antes de contratar
A36: Criterio de aceptación | B36: Caso a recorrer | C36: Resultado que se exige | D36: Medición
A37: Contexto continuo | B37: Pasar de propuesta a chat y a persona | C37: La persona recibe máquina, modalidad, intención, cambios y referencia; el cliente no repite el diagnóstico | D37: Conversaciones transferidas con contexto completo / transferencias; meta por definir en piloto
A38: Control de envío | B38: Conversación sin permiso, baja o ventana vencida sin plantilla | C38: Ningún mensaje proactivo sale; se registra el motivo y se ofrece una ruta permitida | D38: Envíos bloqueados por motivo; 0 envíos no autorizados en pruebas de aceptación
A39: Pedido confirmado | B39: Solicitar reposición y luego cancelar antes de confirmar | C39: Se conserva solo un borrador; no nace pedido comercial | D39: Pedidos sin aceptación expresa: 0 en pruebas de aceptación
A40: Caso persistente | B40: Abrir problema, tomarlo una persona y volver al portal | C40: Mismo ticket, responsable y estado; reapertura disponible | D40: Casos reabiertos / cerrados y satisfacción de cierre; línea base por levantar
A41: Sin duplicados | B41: Reenviar el mismo evento y simular reconexión | C41: Un único pedido/ticket y un historial coherente | D41: Duplicados de operación: 0 en pruebas de aceptación
A42: Protección entre cuentas | B42: Consultar referencia de otra cuenta o sucursal no autorizada | C42: Acceso rechazado sin revelar datos | D42: Accesos indebidos: 0 en pruebas de aceptación
A43: Atención prioritaria | B43: Abrir incidencia crítica con campaña activa | C43: Venta proactiva en pausa; caso asignado a postventa, sin perder atención | D43: Tiempo hasta toma humana y resolución, por criticidad; línea base y meta por definir
A44: Fallo visible | B44: Simular caída del canal, ERP o falta de ejecutivo | C44: Estado pendiente real, avance conservado, reintento controlado y alternativa de contacto | D44: Fallos recuperados y tasa de entrega; línea base por levantar
A45: Valor para el cliente | B45: Resolver una consulta sencilla con IA y otra con ejecutivo | C45: Se distingue quién responde, se entiende qué pasó y cuál es el siguiente paso | D45: Resolución sin repetición, satisfacción y abandono; medir ronda 2 y piloto
A47: Fuente primaria | B47: WhatsApp Business Messaging Policy, actualizada el 23-09-2026; consultada el 15-10-2026. https://business.whatsapp.com/policy
A48: Modalidades | B48: Comodato con compra mensual de insumos. Montos de demostración académica; precio, stock, cobertura y condiciones los confirma la ejecutiva.

Sheet 24_CONEXIONES
A1: Viabilidad técnica: qué se puede conectar y qué falta demostrar
A2: Consulta pública 15-10-2026 y diagnóstico externo 27-08-2026. V = recurso público/lectura comprobada; H = detección histórica; P = acceso o implementación pendiente; D = demostración local. Ninguna V por sí sola prueba operación privada.
A4: ID | B4: Conexión | C4: Estado | D4: Evidencia y alcance | E4: Recurso verificable | F4: Fuente primaria / referencia | G4: Qué habilita | H4: Acceso requerido | I4: Prueba de aceptación | J4: Dependencia / límite
A5: I00 | B5: Catálogo público y huellas del sitio Marley | C5: V / P | D5: Lectura pública 15-10-2026: inicio HTTP 200 con generador VTEX y recurso Connectif; catálogo HTTP 206 con un producto. Evidencia guardada por el equipo. | E5: GET público de catálogo con _from=0&_to=0; una lectura no equivale a permisos de pedido o inventario privado. | F5: https://www.marleycoffee.cl/api/catalog_system/pub/products/search?_from=0&_to=0 | G5: Leer información pública de producto para preparar una recomendación con referencia identificable. | H5: Lectura pública de catálogo; toda escritura comercial y acceso privado requieren autorización aparte. | I5: La respuesta de lectura contiene productId y campos de producto; si falla, mostrar dato no disponible, sin inventarlo. | J5: P: permisos privados, sincronización completa, límites de uso y catálogo B2B.
A6: I01 | B6: VTEX: catálogo y operación | C6: V / P | D6: VTEX observado en auditoría externa 27-08 y lectura de inicio/catálogo 15-10-2026. Orders privado solo tiene documentación pública verificada. | E6: Orders API: GET /api/oms/pvt/orders/{orderId}; autenticación de integración documentada. | F6: https://developers.vtex.com/docs/api-reference/orders-api | G6: Consultar pedidos, estados y referencias para conservar contexto en CRM. | H6: Cuenta VTEX y credenciales con permisos mínimos; entorno de prueba autorizado. | I6: Consultar un pedido de prueba de la cuenta correcta; rechazar referencia ajena sin exponer datos. | J6: P: acceso de Marley Coffee y mapeo catálogo, SKU y sucursal.
A7: I02 | B7: VTEX: reposición confirmada | C7: V / P | D7: Fuente de MVP API_MAP contiene /v1/pedidos, que es un contrato propio propuesto, no una ruta oficial de VTEX. | E7: Checkout API: orderForm, simulación, datos del carrito y flujo autorizado de cierre. | F7: https://developers.vtex.com/docs/api-reference/checkout-api | G7: Preparar y validar la reposición; crearla solo tras la aceptación expresa y el flujo comercial habilitado. | H7: Identidad de cliente, configuración B2B y operación de checkout autorizada. | I7: Cancelar un borrador y comprobar que no hay pedido; confirmar otro y correlacionarlo con una única orden. | J7: P: condiciones B2B, stock, precios, permisos y manejo secuencial de modificaciones.
A8: I03 | B8: VTEX: cambios de pedido hacia ERP | C8: V / P | D8: Capacidad pública documentada; no se ha accedido al ERP real de Marley Coffee. | E8: Orders Feed / Hook y guía Set up order integration. | F8: https://developers.vtex.com/docs/guides/erp-integration-set-up-order-integration | G8: Recibir cambios de estado y llevar una orden autorizada al sistema operativo sin duplicarla. | H8: Credenciales VTEX; adaptador; interfaz y permisos del ERP por confirmar. | I8: Repetir un mismo evento y comprobar una sola operación y acuse; registrar caída y recuperación. | J8: P: marca/API del ERP no informadas; si no hay interfaz, revisión humana con archivo controlado.
A9: I04 | B9: Correos de pedido: VTEX Message Center | C9: V / P | D9: VTEX Message Center aparece en diagnóstico técnico del equipo; documentación pública confirma plantillas transaccionales de pedido. | E9: Plantillas de eventos de pedido y Message Center API. | F9: https://developers.vtex.com/docs/api-reference/message-center-api | G9: Avisar eventos reales de compra, pago y despacho. No demuestra por sí solo nutrición o recuperación de abandono. | H9: Acceso a plantillas y remitente; configuración y pruebas de entregabilidad. | I9: Evento de pedido de prueba genera una única notificación con referencia correcta; un fallo queda visible. | J9: P: confirmar uso actual, plantillas, identidad remitente y reglas para evitar doble correo.
A10: I05 | B10: Connectif: automatización y contenido | C10: V / P | D10: Recurso Connectif detectado en auditoría externa 27-08 y en HTML público de inicio 15-10. Su presencia no demuestra cuenta habilitada ni automatizaciones activas. | E10: POST /custom-integrations/{id}/custom-event-types/; eventos API/webhook. | F10: https://api-docs.connectif.cloud/connectif-api/reference/custom-event-types/create-custom-event-type?v=latest | G10: Configurar W1/W2, recuperación W4, nutrición W10 y supresión al tomar atención humana; alternativa: orquestador propio. | H10: Cuenta habilitada, credenciales, permisos y esquema de eventos; remitente y finalidades aprobados. | I10: Evento único activa una secuencia autorizada; atención humana o baja la detiene; reintento no duplica correo. | J10: P: plan/configuración y derechos de uso reales; no se presupone que ya existen esos flujos.
A11: I06 | B11: GA4 y Google Tag Manager | C11: V / P / D | D11: GTM y configuración sendGA4EventsValue=true observados en HTML de inicio 15-10; no demuestran recepción efectiva en GA4. Auditoría 27-08 detecta GA4/GTM. | E11: Measurement Protocol; Google tag/GTM para navegador. api_secret se conserva en servidor. | F11: https://developers.google.com/analytics/devguides/collection/protocol/ga4/sending-events | G11: Medir eventos, origen y embudo con identificadores internos minimizados, separados de los datos personales del CRM. | H11: Propiedad y flujo de datos autorizados, permisos GTM/GA4 y configuración de consentimiento. | I11: Verificar eventos de prueba y atribución; no enviar correo, teléfono ni conversación a analítica. | J11: P: propiedad, consentimiento y validación de eventos. D: la bitácora local no prueba recepción en GA4.
A12: I07 | B12: Mercado Pago | C12: V / H / P | D12: Medio de pago identificado según diagnóstico del equipo; una huella pública no da acceso a transacciones. | E12: Credenciales de prueba/producción y Access Token de servidor. | F12: https://www.mercadopago.cl/developers/es/docs/adobe-commerce/resources/credentials | G12: Reutilizar el medio de pago habilitado por la tienda, sin recoger tarjetas dentro del chat. | H12: Cuenta comercial y credenciales del producto elegido; confirmar integración existente antes de modificarla. | I12: En entorno autorizado de pruebas, correlacionar pago y pedido, incluido rechazo; nunca simular pago como aprobado. | J12: P: contratación, modalidad de checkout y permisos. La entrega académica no realiza cobros.
A13: I08 | B13: Webpay / Transbank | C13: V / H / P | D13: Medio de pago identificado en diagnóstico; el portal oficial de Transbank describe herramientas para integrar sus productos. | E13: Documentación y herramientas Webpay Plus referidas por el centro de ayuda oficial. | F13: https://publico.transbank.cl/es/web/centro-de-ayuda/que-informacion-puedo-encontrar-en-el-portal-Transbank-Developers | G13: Mantener la ruta de pago de la tienda habilitada, con respuesta transaccional verificada. | H13: Comercio, configuración y entorno de integración autorizado; credenciales por confirmar. | I13: Recorrer pago de prueba aprobado, rechazado y abandonado, sin marcar orden pagada sin confirmación válida. | J13: P: configuración real, contrato y pruebas; sin presupuesto ni tarifas supuestas.
A14: I09 | B14: Blue Express / rutas propias | C14: V / P | D14: Blue Express es una alternativa logística del diseño previo por confirmar. La auditoría externa detectó «Blue», lo que no basta para identificar Blue Express ni un contrato. | E14: Centro de ayuda de integraciones y seguimiento ecommerce. | F14: https://www.blue.cl/nosotros/centro-de-ayuda/integraciones-ecommerce | G14: Consultar y mostrar seguimiento cuando exista integración habilitada; conservar alternativa de coordinación logística. | H14: Confirmar cuenta/contrato, interfaz, cobertura y permisos; rutas propias desde la operación interna. | I14: Estado real de un envío de prueba coincide con portal/CRM; si no hay respuesta, mostrar por confirmar. | J14: P: interfaz y credenciales no verificadas. No se inventan endpoint, cobertura ni fecha de entrega.
A15: I10 | B15: WhatsApp Business Platform | C15: V / P / D | D15: Canal nuevo propuesto para el MVP; la política pública no prueba una cuenta o un número habilitados. | E15: Permiso, baja, ventana de atención, plantillas y escalamiento humano; Cloud API propuesta. | F15: https://business.whatsapp.com/policy | G15: Continuar una gestión con contexto y actualizar servicio/postventa sin abrir un caso aislado. | H15: Cuenta, número, permisos técnicos, finalidades, plantillas y adaptador a definir con Marley Coffee. | I15: Bloquear mensaje sin permiso o sin plantilla cuando corresponda; transferir a persona; conservar ticket único. | J15: P: alta y configuración; D: conversación simulada. No hay envío real ni número inventado.
... A21: I16 | B21: Clarity y gobierno de etiquetas | C21: V / H / P | D21: Clarity detectado en auditoría externa 27-08 con advertencia de múltiples etiquetas. No se prueba el estado actual ni se deduce ausencia de una lectura estática. | E21: Guía oficial de instalación del seguimiento Clarity; revisión de etiquetas por propietario/finalidad. | F21: https://learn.microsoft.com/en-us/clarity/setup-and-installation/clarity-setup | G21: Revisar fricción de navegación y duplicidades una vez configurada privacidad y acceso. No usar grabaciones como dato transaccional. | H21: Acceso al proyecto y gestor de etiquetas; controles de consentimiento, exclusiones y retención definidos. | I21: Un recorrido autorizado produce la evidencia prevista sin duplicar etiquetas ni capturar datos sensibles; revisar con responsable de privacidad. | J21: P: proyecto y configuración; no se presupone una API de escritura ni acceso a grabaciones de clientes.
A23: Nivel de evidencia | B23: Qué demuestra | C23: Qué no demuestra
A24: Técnica pública | B24: La documentación describe una capacidad disponible del proveedor. | C24: No demuestra contrato, credenciales, configuración ni acceso a datos de Marley Coffee.
A25: Demostración local | B25: Puntaje, asignación, secuencias y estados se muestran con los datos del MVP. | C25: No equivale a envío real de correo o WhatsApp ni a escritura en ERP.
A26: Piloto conectado | B26: Cada adaptador requiere acceso autorizado, prueba de ida/vuelta y conciliación de referencias. | C26: Solo después se puede declarar conectado ese sistema y ese caso de uso.
A28: Capa | B28: Estado | C28: Función y conexión
A29: 1. Ecosistema existente | B29: V / P | C29: VTEX: catálogo y pedidos; pagos según diagnóstico; ERP, tickets y logística por confirmar. Reutilizar interfaces habilitadas.
A30: 2. Capa de integración | B30: P | C30: Adaptadores por sistema, eventos normalizados, identidad y permisos, cola persistente, deduplicación y recuperación. Contratos /v1 propuestos.
A31: 3. CRM y agentes | B31: D / P | C31: Una cuenta y una conversación con responsable. Puntaje trazable, propuesta sugerida, tareas y traspaso humano con contexto.
A32: 4. Canales coordinados | B32: V / P / D | C32: Chat web consultivo y correo comercial. WhatsApp: postventa iniciada por cliente. Pedido: Message Center. Nutrición por correo autorizado.
A33: 5. Medición y mejora | B33: V / P / D | C33: Bitácora técnica y comercial; eventos mínimos a GA4 autorizado. Resultado de pedido/ticket vuelve al CRM; ajustar por evidencia.
